{"category": "1854", "countryCode": [["\u897f\u73ed\u7259", "es", "118"], ["\u7f8e\u56fd", "us", "11"]], "legalStatus": [["\u672a\u77e5", "125"], ["\u5931\u6548\u4e13\u5229", "4"]], "applicationYear": [["1854", "129"]], "documentYear": [["1935", "1"], ["1934", "4"], ["1885", "1"], ["1884", "1"], ["1869", "4"], ["1864", "8"], ["1859", "19"], ["1855", "58"], ["1854", "33"]], "applicant": [["CHENOT A", "3"], ["IBARRA & CIA", "3"], ["VILALLONGA J", "3"], ["CLAUSOLLES EMILIO", "2"], ["COLLET FRANCISCO", "2"], ["DIAZ FRANCISCO", "2"], ["MOLLINEDO Y CARRATALA MANUEL", "2"], ["PINEAU ANDRES", "2"], ["SHEPARD EDUARDO CLARENCIO", "2"], ["SIMOUNET AUGUSTO", "2"], ["SORIANO Y GARRIDO DONATO", "2"], ["ABREU GABRIEL", "1"], ["ADAM ETIENNE LUIS", "1"], ["ALSINA Y TORRAS JOSE", "1"], ["ALSINA Y TORRAS MELCHOR", "1"], ["AMEZUA JUAN", "1"], ["ANDRE GUSTAVE", "1"], ["ARNAU Y NAVARRO JOSE", "1"], ["ARTHAC FELIPE HECTOR", "1"], ["AZEMA JULIO & CIA", "1"], ["BALAGUER FRANCISCO", "1"], ["BARRAU JACINTO", "1"], ["BAUTISTA BRUNO", "1"], ["BERDAN HIRAM", "1"], ["BOCQUET MR", "1"], ["BONAPLATA NARCISO", "1"], ["BONELLI GAETAN", "1"], ["BOULLOSA Y AMADOR FERNANDO", "1"], ["BOUVET JULIAN LUIS", "1"], ["BOUVIER LUCIANO", "1"], ["BOUVIER VICTOR", "1"], ["BOYER ANTONIO MARIA", "1"], ["BRIANSO AGUSTIN", "1"], ["BURGOS AUGUSTO DE", "1"], ["CAPISTRANO DOMINGUEZ JUAN", "1"], ["CARPENTIER LUIS JOSE NICOLAS", "1"], ["CARRERES JUAN ANTONIO", "1"], ["CEBALLOS ORDONO JOSE DE", "1"], ["COMPANY JOAQUIN", "1"], ["CONAILHAC VICTOR", "1"], ["CONRAD & CANDERAL & MARTINEZ", "1"], ["CORNEAUX PEDRO ANTONIO", "1"], ["COTTE & CIA", "1"], ["CUESTA Y MARTINEZ JUANA", "1"], ["CUNLIFFE LISTER SAMUEL", "1"], ["DABBENE CASIMIRO", "1"], ["DABBENE CELESTINO", "1"], ["DECASTRO J", "1"], ["DECOMBES JUAN MARIA CARLOS", "1"], ["DECOSTER PEDRO ANDRES", "1"], ["DOBRANICH DAMIAN", "1"], ["DOEBS FRANCISCO JULIAN", "1"], ["DOMINE ANTONIO", "1"], ["DUEROS ELIAS", "1"], ["EMERSON BAKER GUILLERM", "1"], ["ESTUBLIE EVARISTO", "1"], ["EWALD M", "1"], ["FALCO JUAN", "1"], ["FOLEY EDMOND LOUIS", "1"], ["GAMERO FRANCISCO", "1"], ["GAZAGNAIRE JORGE & CIA", "1"], ["GIL Y MONTANA JOSE", "1"], ["GOICOERROTEA JUAN GREGORIO", "1"], ["GOMEZ Y REY JUAN", "1"], ["GRAU Y BARNOLA PEDRO", "1"], ["GUYARD FRANCISCO VICTOR", "1"], ["HEBRARD ANTONIO", "1"], ["HECTOR PEDRO JUAN BAUTISTA", "1"], ["HERLUISON HIPOLITO", "1"], ["HERNANDEZ LORENZO", "1"], ["IRIGOYEN JUAN MIGUEL", "1"], ["JACKSON JAMES & HIJOS", "1"], ["JORDANA JOSE ANTONIO", "1"], ["JULIENNE AGUSTIN", "1"], ["KARR EUGENIO & CIA", "1"], ["KOECHLIN A", "1"], ["LAGRANGE PABLO", "1"], ["LAVERDET MR", "1"], ["LEBON LUIS", "1"], ["LION CLAUDIO", "1"], ["LIZARBE PASCASIO & CIA", "1"], ["LLAMAS Y GOMEZ ENRIQUE", "1"], ["LUCET MANUEL", "1"], ["LUZARCHE ANTONIO", "1"], ["MAGNAT ANTONIO", "1"], ["MAMBY JOSE LANE", "1"], ["MANTILLA Y GARCIA JOSE", "1"], ["MARTINEZ DOMINGO JOSE", "1"], ["MARTINEZ LOPEZ PEDRO", "1"], ["MIGUEL TOMAS DE", "1"], ["MOLON RENATO CARLOS MARIA DE", "1"], ["MONSERRAT JUAN BAUTISTA", "1"], ["MORAND PEDRO", "1"], ["MUNOZ AMADOR DEMETRIO", "1"], ["NEGRIER ENRIQUE FORTUNATO", "1"], ["OBARRIOS GUTIERREZ DOLORES", "1"], ["ORRISSE GROWER GUILLERMO", "1"], ["ORTIGOSA MANUEL", "1"], ["PASCAL JUAN BAUTISTA & CIA", "1"], ["PERELLI ERCOLINI GIOVANNI", "1"]], "applicantCountryCode": [[null, "0"]], "inventor": [["Abraham Cooperstein", "1"], ["Andeew Buegess", "1"], ["Charles C. Puckett", "1"], ["Herman E. De Vries", "1"], ["Lnrelle Guild", "1"], ["Vincent De Liso", "1"]], "ipc": [["C12A", "9"], ["C22B", "9"], ["C10A", "6"], ["F27B", "5"], ["D01B", "4"], ["D06A", "4"], ["F03A", "4"], ["F04A", "4"], ["A43D", "3"], ["B02C", "3"], ["B28A", "3"], ["C05A", "3"], ["D01A", "3"], ["D03A", "3"], ["A21A", "2"], ["A22A", "2"], ["A23G", "2"], ["B41A", "2"], ["C09A", "2"], ["C11B", "2"], ["C13A", "2"], ["C21A", "2"], ["D05B", "2"], ["F41C", "2"], ["H04L", "2"], ["A01M", "1"], ["A21B", "1"], ["A21C", "1"], ["A23N", "1"], ["A44B", "1"], ["A47C", "1"], ["A61K", "1"], ["B28B", "1"], ["B28D", "1"], ["B41B9/10", "1"], ["B41D3/00", "1"], ["B61A", "1"], ["B61H", "1"], ["B68B", "1"], ["C04A", "1"], ["C06F", "1"], ["C10B", "1"], ["C10F", "1"], ["C10J", "1"], ["C11A", "1"], ["C23A", "1"], ["C23D", "1"], ["C23F", "1"], ["D03D", "1"], ["E03F", "1"], ["E04B", "1"], ["F01B", "1"], ["F16J", "1"], ["F21V8/00", "1"], ["F22A", "1"], ["F22B", "1"], ["F25D", "1"], ["G03A", "1"], ["G04B19/24", "1"], ["G04B19/253", "1"], ["G10B", "1"], ["G10D", "1"], ["H02A", "1"]], "ipc1": [["C", "44"], ["F", "21"], ["D", "17"], ["A", "16"], ["B", "14"], ["G", "4"], ["H", "3"], ["E", "2"]], "ipc2": [["C10", "9"], ["C12", "9"], ["C22", "9"], ["D01", "7"], ["B28", "5"], ["F27", "5"], ["A21", "4"], ["D03", "4"], ["D06", "4"], ["F03", "4"], ["F04", "4"], ["A23", "3"], ["A43", "3"], ["B02", "3"], ["B41", "3"], ["C05", "3"], ["C11", "3"], ["C23", "3"], ["A22", "2"], ["B61", "2"], ["C09", "2"], ["C13", "2"], ["C21", "2"], ["D05", "2"], ["F22", "2"], ["F41", "2"], ["G10", "2"], ["H04", "2"], ["A01", "1"], ["A44", "1"], ["A47", "1"], ["A61", "1"], ["B68", "1"], ["C04", "1"], ["C06", "1"], ["E03", "1"], ["E04", "1"], ["F01", "1"], ["F16", "1"], ["F21", "1"], ["F25", "1"], ["G03", "1"], ["G04", "1"], ["H02", "1"]], "ipc3": [["C12A", "9"], ["C22B", "9"], ["C10A", "6"], ["F27B", "5"], ["D01B", "4"], ["D06A", "4"], ["F03A", "4"], ["F04A", "4"], ["A43D", "3"], ["B02C", "3"], ["B28A", "3"], ["C05A", "3"], ["D01A", "3"], ["D03A", "3"], ["A21A", "2"], ["A22A", "2"], ["A23G", "2"], ["B41A", "2"], ["C09A", "2"], ["C11B", "2"], ["C13A", "2"], ["C21A", "2"], ["D05B", "2"], ["F41C", "2"], ["H04L", "2"], ["A01M", "1"], ["A21B", "1"], ["A21C", "1"], ["A23N", "1"], ["A44B", "1"], ["A47C", "1"], ["A61K", "1"], ["B28B", "1"], ["B28D", "1"], ["B41B", "1"], ["B41D", "1"], ["B61A", "1"], ["B61H", "1"], ["B68B", "1"], ["C04A", "1"], ["C06F", "1"], ["C10B", "1"], ["C10F", "1"], ["C10J", "1"], ["C11A", "1"], ["C23A", "1"], ["C23D", "1"], ["C23F", "1"], ["D03D", "1"], ["E03F", "1"], ["E04B", "1"], ["F01B", "1"], ["F16J", "1"], ["F21V", "1"], ["F22A", "1"], ["F22B", "1"], ["F25D", "1"], ["G03A", "1"], ["G04B", "1"], ["G10B", "1"], ["G10D", "1"], ["H02A", "1"]], "ipc4": [["B41B9", "1"], ["B41D3", "1"], ["F21V8", "1"], ["G04B19", "1"]], "ipc5": [["B41B9/10", "1"], ["B41D3/00", "1"], ["F21V8/00", "1"], ["G04B19/24", "1"], ["G04B19/253", "1"]], "loc": [[null, "0"]]}