{"category": "1990", "countryCode": [["\u65e5\u672c", "jp", "646084"], ["\u6b27\u76df", "ep", "136689"], ["\u5fb7\u56fd", "de", "128142"], ["\u7f8e\u56fd", "us", "109433"], ["\u97e9\u56fd", "kr", "103467"], ["\u82f1\u56fd", "gb", "48325"], ["\u52a0\u62ff\u5927", "ca", "46078"], ["\u4e2d\u56fd", "cn", "40163"], ["\u610f\u5927\u5229", "it", "37051"], ["\u6fb3\u5927\u5229\u4e9a", "au", "36826"], ["\u4fc4\u7f57\u65af", "ru", "35110"], ["\u82cf\u8054", "su", "31822"], ["\u6cd5\u56fd", "fr", "26115"], ["\u897f\u73ed\u7259", "es", "25624"], ["\u5965\u5730\u5229", "at", "20313"], ["\u4e2d\u56fd\u53f0\u6e7e", "tw", "20009"], ["WIPO", "wo", "19978"], ["\u632a\u5a01", "no", "15215"], ["\u82ac\u5170", "fi", "14235"], ["\u4e39\u9ea6", "dk", "14174"], ["\u5308\u7259\u5229", "hu", "11431"], ["\u5df4\u897f", "br", "10836"], ["\u745e\u5178", "se", "8579"], ["\u5357\u975e", "za", "6981"], ["\u6ce2\u5170", "pl", "6897"], ["\u4e1c\u5fb7", "dd", "6837"], ["\u7231\u5c14\u5170", "ie", "5928"], ["\u4ee5\u8272\u5217", "il", "5490"], ["\u8461\u8404\u7259", "pt", "5380"], ["\u6377\u514b\u65af\u6d1b\u4f10\u514b", "cs", "4902"], ["\u8377\u5170", "nl", "3079"], ["\u65b0\u897f\u5170", "nz", "3074"], ["\u5e0c\u814a", "gr", "2641"], ["\u5370\u5ea6", "in", "2200"], ["\u745e\u58eb", "ch", "2139"], ["\u4e4c\u514b\u5170", "ua", "1990"], ["\u58a8\u897f\u54e5", "mx", "1936"], ["\u6377\u514b", "cz", "1908"], ["\u5357\u65af\u62c9\u592b", "yu", "1745"], ["\u7f57\u9a6c\u5c3c\u4e9a", "ro", "1713"], ["\u65b0\u52a0\u5761", "sg", "1335"], ["\u963f\u6839\u5ef7", "ar", "1104"], ["\u4e2d\u56fd\u9999\u6e2f", "hk", "1094"], ["\u4fdd\u52a0\u5229\u4e9a", "bg", "1005"], ["\u6bd4\u5229\u65f6", "be", "920"], ["\u571f\u8033\u5176", "tr", "777"], ["\u65af\u6d1b\u4f10\u514b", "sk", "742"], ["\u83f2\u5f8b\u5bbe", "ph", "700"], ["\u6469\u6d1b\u54e5", "ma", "321"], ["\u975e\u6d32\u77e5\u8bc6\u4ea7\u6743\u7ec4\u7ec7", "oa", "309"], ["\u57c3\u53ca", "eg", "292"], ["\u65af\u6d1b\u6587\u5c3c\u4e9a", "si", "223"], ["\u5362\u68ee\u5821", "lu", "209"], ["\u5384\u74dc\u591a\u5c14", "ec", "207"], ["\u51b0\u5c9b", "is", "168"], ["\u79d8\u9c81", "pe", "166"], ["\u7a81\u5c3c\u65af", "tn", "160"], ["\u6d25\u5df4\u5e03\u97e6", "zw", "146"], ["\u975e\u6d32\u5730\u533a\u5de5\u4e1a\u4ea7\u6743\u7ec4\u7ec7", "ap", "142"], ["\u5371\u5730\u9a6c\u62c9", "gt", "107"], ["\u6469\u7eb3\u54e5", "mc", "105"], ["\u6c99\u7279\u963f\u62c9\u4f2f", "sa", "83"], ["\u53e4\u5df4", "cu", "64"], ["\u963f\u5c14\u53ca\u5229\u4e9a", "dz", "57"], ["\u7ea6\u65e6", "jo", "52"], ["\u8d5e\u6bd4\u4e9a", "zm", "45"], ["\u8d8a\u5357", "vn", "39"], ["\u9a6c\u6765\u897f\u4e9a", "my", "37"], ["\u9a6c\u62c9\u7ef4", "mw", "35"], ["\u585e\u6d66\u8def\u65af", "cy", "33"], ["\u9a6c\u8033\u4ed6", "mt", "29"], ["\u4e4c\u62c9\u572d", "uy", "9"], ["\u591a\u7c73\u5c3c\u52a0", "do", "6"], ["\u6469\u5c14\u591a\u74e6", "md", "6"], ["\u54e5\u4f26\u6bd4\u4e9a", "co", "4"], ["\u683c\u9c81\u5409\u4e9a", "ge", "4"], ["\u8428\u5c14\u74e6\u591a", "sv", "4"], ["\u5df4\u62ff\u9a6c", "pa", "3"], ["\u54e5\u65af\u8fbe\u9ece\u52a0", "cr", "1"]], "legalStatus": [["\u5931\u6548\u4e13\u5229", "1020403"], ["\u672a\u77e5", "585459"], ["\u65e0\u6548\u4e13\u5229", "35242"], ["\u516c\u5f00", "19978"], ["\u5b9e\u8d28\u5ba1\u67e5", "194"], ["\u6709\u6548\u4e13\u5229", "6"]], "applicationYear": [["1990", "1661282"]], "documentYear": [["2020", "4"], ["2019", "2"], ["2018", "1"], ["2017", "2"], ["2016", "10"], ["2015", "16"], ["2014", "14"], ["2013", "28"], ["2012", "29"], ["2011", "41"], ["2010", "68"], ["2009", "116"], ["2008", "147"], ["2007", "255"], ["2006", "395"], ["2005", "671"], ["2004", "926"], ["2003", "1266"], ["2002", "2976"], ["2001", "6925"], ["2000", "18039"], ["1999", "40631"], ["1998", "33106"], ["1997", "41315"], ["1996", "57523"], ["1995", "83470"], ["1994", "98358"], ["1993", "114165"], ["1992", "542343"], ["1991", "451836"], ["1990", "166484"], ["1989", "11"], ["1988", "13"], ["1987", "29"], ["1986", "29"], ["1985", "23"], ["1984", "8"], ["1983", "5"], ["1982", "1"], ["1981", "1"]], "applicant": [["Nec Corp", "16861"], ["Matsushita Electric Ind Co Ltd", "15964"], ["Toshiba Corp", "14252"], ["Mitsubishi Electric Corp", "13403"], ["Fujitsu Ltd", "12903"], ["Hitachi Ltd", "12153"], ["Canon Inc", "9994"], ["\uc0bc\uc131\uc804\uc790\uc8fc\uc2dd\ud68c\uc0ac", "8168"], ["\uc8fc\uc2dd\ud68c\uc0ac \uc5d8\uc9c0\uc774\uc544\uc774", "7111"], ["Ricoh Co Ltd", "6137"], ["\u677e\u4e0b\u96fb\u5668\u7523\u696d\u682a\u5f0f\u4f1a\u793e", "4788"], ["Seiko Epson Corp", "4022"], ["Sony Corp", "3986"], ["Sharp Corp", "3966"], ["Sanyo Electric Co Ltd", "3857"], ["BAYER AG", "3796"], ["\u65e5\u672c\u96fb\u6c17\u682a\u5f0f\u4f1a\u793e", "3677"], ["Fuji Photo Film Co Ltd", "3491"], ["Konica Corp", "3264"], ["Nippon Telegr & Teleph Corp <Ntt>", "3183"], ["Matsushita Electric Works Ltd", "3172"], ["\u682a\u5f0f\u4f1a\u793e\u6771\u829d", "3145"], ["SIEMENS AG", "3043"], ["\u4e09\u83f1\u96fb\u6a5f\u682a\u5f0f\u4f1a\u793e", "2950"], ["HOECHST AG", "2917"], ["\u30ad\u30e4\u30ce\u30f3\u682a\u5f0f\u4f1a\u793e", "2875"], ["Nippon Steel Corp", "2850"], ["\u682a\u5f0f\u4f1a\u793e\u65e5\u7acb\u88fd\u4f5c\u6240", "2822"], ["Mitsubishi Heavy Ind Ltd", "2816"], ["\u5bcc\u58eb\u901a\u682a\u5f0f\u4f1a\u793e", "2796"], ["Oki Electric Ind Co Ltd", "2647"], ["Nissan Motor Co Ltd", "2644"], ["Fuji Electric Co Ltd", "2591"], ["\ub300\uc6b0\uc804\uc790\uc8fc\uc2dd\ud68c\uc0ac", "2379"], ["\ud604\ub300\ubc18\ub3c4\uccb4 \uc8fc\uc2dd\ud68c\uc0ac", "2304"], ["Mazda Motor Corp", "2258"], ["GEN ELECTRIC", "2257"], ["DU PONT", "2185"], ["BASF AG", "2181"], ["SIEMENS AKTIENGESELLSCHAFT", "2164"], ["Kubota Corp", "2145"], ["Toyota Motor Corp", "2101"], ["ICI PLC", "2067"], ["\uac00\ubd80\uc2dc\ub07c\uac00\uc774\uc0e4 \ub3c4\uc2dc\ubc14", "2055"], ["\u4e09\u6d0b\u96fb\u6a5f\u682a\u5f0f\u4f1a\u793e", "2049"], ["MITSUBISHI ELECTRIC CORP", "2047"], ["CIBA GEIGY AG", "2019"], ["Kawasaki Steel Corp", "1987"], ["Brother Ind Ltd", "1982"], ["International Business Machines\nCorporation", "1971"], ["CANON KABUSHIKI KAISHA", "1942"], ["Sumitomo Electric Ind Ltd", "1942"], ["CANON KK", "1935"], ["KABUSHIKI KAISHA TOSHIBA", "1929"], ["BOSCH GMBH ROBERT", "1922"], ["Olympus Optical Co Ltd", "1901"], ["\u682a\u5f0f\u4f1a\u793e\u30ea\u30b3\u30fc", "1818"], ["IBM", "1810"], ["\uc0bc\uc131\uc5d0\uc2a4\ub514\uc544\uc774 \uc8fc\uc2dd\ud68c\uc0ac", "1782"], ["PROCTER & GAMBLE", "1718"], ["\u30bd\u30cb\u30fc\u682a\u5f0f\u4f1a\u793e", "1703"], ["\u677e\u4e0b\u96fb\u5de5\u682a\u5f0f\u4f1a\u793e", "1703"], ["PFIZER", "1622"], ["Sekisui Chem Co Ltd", "1616"], ["\uc5d0\uc2a4\ucf00\uc774\ud558\uc774\ub2c9\uc2a4 \uc8fc\uc2dd\ud68c\uc0ac", "1610"], ["UNILEVER PLC", "1607"], ["DOW CHEMICAL CO", "1602"], ["Philips Electronics N.V.", "1512"], ["MINNESOTA MINING & MFG", "1501"], ["\u4e09\u83f1\u91cd\u5de5\u696d\u682a\u5f0f\u4f1a\u793e", "1489"], ["\uc0bc\uc131\uc804\uae30\uc8fc\uc2dd\ud68c\uc0ac", "1479"], ["Nkk Corp", "1433"], ["Asahi Chem Ind Co Ltd", "1409"], ["Fuji Xerox Co Ltd", "1407"], ["\u30b7\u30e3\u30fc\u30d7\u682a\u5f0f\u4f1a\u793e", "1375"], ["Honda Motor Co Ltd", "1328"], ["FUJITSU LIMITED", "1326"], ["Sumitomo Metal Ind Ltd", "1311"], ["Kobe Steel Ltd", "1294"], ["\u65e5\u672c\u96fb\u4fe1\u96fb\u8a71\u682a\u5f0f\u4f1a\u793e", "1292"], ["Tokyo Electric Co Ltd", "1291"], ["SONY CORP", "1282"], ["\ud604\ub300\uc790\ub3d9\ucc28\uc8fc\uc2dd\ud68c\uc0ac", "1281"], ["\u65b0\u65e5\u672c\u88fd\u9435\u682a\u5f0f\u4f1a\u793e", "1275"], ["HENKEL KGAA", "1273"], ["BASF Aktiengesellschaft", "1266"], ["EASTMAN KODAK COMPANY", "1263"], ["SONY CORPORATION", "1256"], ["Nippondenso Co Ltd", "1233"], ["Shimadzu Corp", "1227"], ["PHILIPS NV", "1214"], ["Nec Eng Ltd", "1212"], ["\u5bcc\u58eb\u5199\u771f\u30d5\u30a4\u30eb\u30e0\u682a\u5f0f\u4f1a\u793e", "1211"], ["Furukawa Electric Co Ltd:The", "1197"], ["Mita Ind Co Ltd", "1195"], ["TOSHIBA KAWASAKI KK", "1185"], ["\u65e5\u7523\u81ea\u52d5\u8eca\u682a\u5f0f\u4f1a\u793e", "1185"], ["Minolta Camera Co Ltd", "1179"], ["Omron Corp", "1171"], ["\u682a\u5f0f\u4f1a\u793e\u30af\u30dc\u30bf", "1170"]], "applicantCountryCode": [["\u7f8e\u56fd", "131600"], ["\u65e5\u672c", "98355"], ["\u5fb7\u56fd", "95413"], ["\u82cf\u8054", "56693"], ["\u6cd5\u56fd", "45041"], ["\u4e2d\u56fd", "32123"], ["\u82f1\u56fd", "28602"], ["\u610f\u5927\u5229", "19898"], ["\u745e\u58eb", "15991"], ["\u97e9\u56fd", "13032"], ["\u8377\u5170", "12963"], ["\u4e2d\u56fd\u53f0\u6e7e", "12299"], ["\u745e\u5178", "12260"], ["\u82ac\u5170", "9703"], ["\u52a0\u62ff\u5927", "7051"], ["\u4fc4\u7f57\u65af", "6999"], ["\u5965\u5730\u5229", "6142"], ["\u5df4\u897f", "5284"], ["\u6ce2\u5170", "5072"], ["\u4e39\u9ea6", "4726"], ["\u6377\u514b\u65af\u6d1b\u4f10\u514b", "4169"], ["\u897f\u73ed\u7259", "3812"], ["\u6bd4\u5229\u65f6", "3176"], ["\u6fb3\u5927\u5229\u4e9a", "3081"], ["\u632a\u5a01", "2683"], ["\u6b27\u76df", "2228"], ["\u4e4c\u514b\u5170", "2161"], ["\u5308\u7259\u5229", "1820"], ["\u7f57\u9a6c\u5c3c\u4e9a", "1501"], ["\u4ee5\u8272\u5217", "1212"], ["\u4e1c\u5fb7", "849"], ["\u7231\u5c14\u5170", "836"], ["\u6377\u514b", "775"], ["\u5217\u652f\u6566\u58eb\u767b", "724"], ["\u5357\u65af\u62c9\u592b", "629"], ["\u5357\u975e", "576"], ["\u5362\u68ee\u5821", "565"], ["\u5370\u5ea6", "469"], ["\u672a\u77e5", "287"], ["\u4e2d\u56fd\u9999\u6e2f", "286"], ["\u65b0\u897f\u5170", "237"], ["\u8461\u8404\u7259", "222"], ["\u767d\u4fc4\u7f57\u65af", "200"], ["\u6469\u7eb3\u54e5", "184"], ["\u4fdd\u52a0\u5229\u4e9a", "179"], ["\u83f2\u5f8b\u5bbe", "170"], ["\u58a8\u897f\u54e5", "164"], ["\u5e0c\u814a", "157"], ["\u65af\u6d1b\u4f10\u514b", "155"], ["\u54c8\u8428\u514b\u65af\u5766", "144"], ["\u5f00\u66fc\u7fa4\u5c9b", "133"], ["\u963f\u6839\u5ef7", "109"], ["\u65b0\u52a0\u5761", "93"], ["\u5723\u591a\u7f8e\u548c\u666e\u6797\u897f\u6bd4", "92"], ["\u59d4\u5185\u745e\u62c9", "90"], ["\u5df4\u62ff\u9a6c", "80"], ["\u7231\u6c99\u5c3c\u4e9a", "73"], ["\u571f\u8033\u5176", "67"], ["\u4e4c\u5179\u522b\u514b\u65af\u5766", "62"], ["\u6469\u6d1b\u54e5", "60"], ["\u65af\u6d1b\u6587\u5c3c\u4e9a", "59"], ["\u963f\u585e\u62dc\u7586", "58"], ["\u53e4\u5df4", "58"], ["\u6469\u5c14\u591a\u74e6", "47"], ["\u5854\u5409\u514b\u65af\u5766", "45"], ["\u571f\u5e93\u66fc\u65af\u5766", "45"], ["\u82f1\u5c5e\u7ef4\u5c14\u4eac\u7fa4\u5c9b", "44"], ["\u4e9a\u7f8e\u5c3c\u4e9a", "42"], ["\u683c\u9c81\u5409\u4e9a", "39"], ["\u514b\u7f57\u5730\u4e9a", "35"], ["\u4e4c\u62c9\u572d", "34"], ["\u5409\u5c14\u5409\u65af\u65af\u5766", "33"], ["\u767e\u6155\u5927", "32"], ["\u51b0\u5c9b", "32"], ["\u7a81\u5c3c\u65af", "31"], ["\u62c9\u8131\u7ef4\u4e9a", "25"], ["\u585e\u6d66\u8def\u65af", "24"], ["\u9a6c\u6765\u897f\u4e9a", "23"], ["\u79d8\u9c81", "23"], ["\u76f4\u5e03\u7f57\u9640", "22"], ["\u5df4\u5df4\u591a\u65af", "20"], ["\u5723\u9a6c\u529b\u8bfa", "18"], ["\u6c99\u7279\u963f\u62c9\u4f2f", "17"], ["\u5df4\u54c8\u9a6c", "16"], ["\u7acb\u9676\u5b9b", "15"], ["\u6d25\u5df4\u5e03\u97e6", "14"], ["\u963f\u5c14\u53ca\u5229\u4e9a", "13"], ["\u54e5\u4f26\u6bd4\u4e9a", "12"], ["\u5384\u74dc\u591a\u5c14", "12"], ["\u667a\u5229", "11"], ["\u5370\u5c3c", "9"], ["\u65af\u5a01\u58eb\u5170", "9"], ["\u6cf0\u56fd", "9"], ["\u51e0\u5185\u4e9a", "8"], ["\u57c3\u53ca", "7"], ["\u6bdb\u91cc\u6c42\u65af", "7"], ["\u6ce2\u591a\u9ece\u5404", "7"], ["\u5229\u6bd4\u91cc\u4e9a", "6"], ["\u7ea6\u65e6", "5"], ["\u585e\u5c14\u7ef4\u4e9a", "5"]], "inventor": [["NAME NOT GIVEN", "2916"], ["VERZICHT DES ERFINDERS AUF NENNUNG", "1323"], ["BRAQUET PIERRE", "365"], ["ITO KOJI", "355"], ["EASTMAN KODAK COMPANY", "351"], ["DER ERFINDER WIRD NACHTRAEGLICH BENANNT", "316"], ["TAKAHASHI HIROSHI", "298"], ["NIIYAMA KICHIHEI", "268"], ["SUZUKI HIROSHI", "268"], ["ITO HIROSHI", "251"], ["ROBERT BOSCH GMBH", "245"], ["HANEDA SATORU", "234"], ["SATO HIROSHI", "226"], ["HENKEL KOMMANDITGESELLSCHAFT AUF AKTIEN", "225"], ["FUKUCHI MASAKAZU", "220"], ["GRASSO GIORGIO", "220"], ["TANAKA HIROSHI", "220"], ["OETIKER HANS", "219"], ["SUZUKI TAKASHI", "213"], ["SIEMENS AKTIENGESELLSCHAFT", "212"], ["SILBIGER JAKOB", "208"], ["SERI RANIERO", "206"], ["AMMERMANN EBERHARD", "199"], ["SACHETTO JEAN-PIERRE", "199"], ["LORENZ GISELA", "197"], ["KOBAYASHI HIROSHI", "196"], ["NAKAMURA HIROSHI", "196"], ["SZPORNY LASZLO", "195"], ["LENTZ DAVID JOHN", "190"], ["YAMAMOTO HIROSHI", "188"], ["MOTOROLA, INC.", "187"], ["SATO TAKASHI", "185"], ["MORITA SHIZUO", "182"], ["SATO KOICHI", "182"], ["LAURENT JEAN-PIERRE", "180"], ["TAKAHASHI HIROYUKI", "180"], ["E.I. DU PONT DE NEMOURS AND COMPANY", "177"], ["ALLIED-SIGNAL INC.", "173"], ["ESANU ANDRE", "173"], ["FANUC LTD", "168"], ["NAKAMURA TAKASHI", "168"], ["SUZUKI AKIRA", "163"], ["WATANABE HIROSHI", "163"], ["SATO HISAO", "161"], ["\uae40\uad11\ud0dc", "161"], ["RIGHETTI ALDO", "158"], ["KOBAYASHI TAKASHI", "154"], ["EFFLAND RICHARD CHARLES", "152"], ["FURUKAWA SANEHIRO", "152"], ["KISS BELA", "152"], ["WUERZER BRUNO", "152"], ["SUZUKI HIDEO", "148"], ["UGAWA SHOHACHI", "148"], ["YAMAZAKI SHUNPEI", "145"], ["AMMERMANN EBERHARD DR", "143"], ["LORENZ GISELA DR", "143"], ["TAKAHASHI AKIRA", "141"], ["\ubc15\uc6a9\uaddc", "141"], ["SATO KENICHI", "139"], ["YOSHIDA HIROSHI", "139"], ["FOCKE HEINZ", "138"], ["TAKANASHI RYOYU", "137"], ["OKADA HIROYUKI", "136"], ["THEURER JOSEF", "136"], ["YOSHIKAWA HIROYUKI", "135"], ["KATO EIICHI", "134"], ["TANAKA TAKASHI", "134"], ["WESTPHALEN KARL-OTTO", "134"], ["\ubc31\ub3d9\ucca0", "134"], ["TAKAHASHI KOJI", "133"], ["FERRIERO FELICE", "132"], ["SAUTER HUBERT", "132"], ["TANAKA HIROYUKI", "132"], ["ITO AKIRA", "131"], ["IKEDA TADAYOSHI", "130"], ["INOUE HIROSHI", "130"], ["ITO MASAYOSHI", "130"], ["OGAWA HIROSHI", "128"], ["YAMAMOTO TAKASHI", "128"], ["ISHIDA ISAO", "127"], ["SUZUKI MAKOTO", "127"], ["ITO HIROYUKI", "126"], ["SAITO HIROSHI", "126"], ["TANAKA AKIRA", "126"], ["SUZUKI AKIO", "125"], ["GAMBERINI ANTONIO", "124"], ["SATO SHINICHI", "124"], ["SUZUKI HIROYUKI", "124"], ["KLEIN JOSEPH THOMAS", "123"], ["ROBERTS DAVID ALAN", "123"], ["TANAKA KOJI", "123"], ["BARREAU MICHEL", "122"], ["TAKAHASHI SUSUMU", "122"], ["SHIMOMURA YOSHIKI", "120"], ["TAKAHASHI TSUTOMU", "120"], ["TANAKA AKIO", "120"], ["UMEDA YASUSHI", "120"], ["FONTANA FLAVIO", "119"], ["ITO SUSUMU", "119"], ["MATSUMOTO TAKESHI", "119"]], "ipc": [["A61K38/00", "11101"], ["G03G15/00", "8813"], ["A61P43/00", "8233"], ["C12N15/09", "8219"], ["C07B61/00", "7527"], ["A61P35/00", "5760"], ["C07K14/00", "5515"], ["A61K8/00", "4755"], ["G03G21/00", "4679"], ["A61K31/44", "4533"], ["A61P29/00", "4532"], ["C12P21/02", "4483"], ["H04N1/00", "4379"], ["A61K31/40", "4227"], ["H01L21/027", "3981"], ["A61K", "3904"], ["A61K9/00", "3825"], ["A61K31/70", "3566"], ["H04B7/26", "3520"], ["G01N33/53", "3494"], ["C12N5/10", "3461"], ["C07D", "3460"], ["G06T1/00", "3456"], ["A61K39/395", "3375"], ["H01L21/60", "3304"], ["H01L29/78", "3303"], ["A61K20060101", "3299"], ["A61K31/445", "3231"], ["A61K31/505", "3224"], ["A61K31/495", "3214"], ["G03G15/08", "3181"], ["H01L21/66", "3181"], ["C12R1/91", "3170"], ["G03G15/04", "3148"], ["C12P21/08", "3137"], ["C07D401/12", "3109"], ["A61P9/00", "3106"], ["A61P31/04", "3099"], ["C12Q1/68", "2996"], ["A61P9/10", "2962"], ["C07K16/00", "2953"], ["A61K39/00", "2951"], ["C12N1/21", "2932"], ["A61K31/415", "2912"], ["A61P31/12", "2846"], ["A61P9/12", "2811"], ["C08L101/00", "2811"], ["C08J5/18", "2804"], ["A61K31/00", "2766"], ["A61K31/55", "2749"], ["C07D405/12", "2567"], ["H01L27/04", "2539"], ["A61K31/47", "2529"], ["F02D45/00", "2521"], ["C07D471/04", "2510"], ["C08L83/04", "2499"], ["C07D487/04", "2362"], ["C12P21/00", "2353"], ["H01L21/205", "2350"], ["H04M11/00", "2312"], ["H01L21/822", "2289"], ["C12R1/19", "2284"], ["A61P25/00", "2283"], ["G06F15/16", "2283"], ["A61P25/04", "2275"], ["A61K31/435", "2259"], ["H05K3/34", "2258"], ["H04N5/225", "2253"], ["G06F17/50", "2242"], ["G06F13/00", "2224"], ["H01L21/30", "2222"], ["H04Q9/00", "2201"], ["A61K47/48", "2199"], ["G02B6/00", "2191"], ["A61P7/02", "2189"], ["G11B11/10", "2185"], ["A61P25/28", "2183"], ["C22C38/00", "2183"], ["H04N1/04", "2169"], ["A61P37/08", "2154"], ["G06F12/00", "2140"], ["H04N1/40", "2131"], ["G09F9/00", "2123"], ["A61P17/00", "2111"], ["C07D417/12", "2096"], ["H01S5/00", "2084"], ["C08F10/00", "2079"], ["C07D20060101", "2047"], ["H04N1/32", "2047"], ["A61P37/00", "2041"], ["B01D53/34", "2040"], ["C07D521/00", "2036"], ["H01L21/302", "2028"], ["A61K31/535", "2011"], ["G11B11/105", "2007"], ["C08L67/00", "2000"], ["G06F17/30", "1974"], ["A61K31/19", "1959"], ["H01L21/3205", "1929"], ["C12N15/12", "1926"]], "ipc1": [["B", "434530"], ["G", "376131"], ["H", "328319"], ["C", "304616"], ["A", "287146"], ["F", "200461"], ["E", "98416"], ["D", "47003"]], "ipc2": [["H01", "154195"], ["A61", "138206"], ["G01", "114669"], ["C07", "103937"], ["H04", "97702"], ["F16", "77972"], ["B65", "76256"], ["G06", "74328"], ["C08", "72360"], ["B60", "63433"], ["B01", "55522"], ["G03", "55157"], ["G11", "51433"], ["A01", "47751"], ["A47", "42986"], ["G02", "41884"], ["H02", "40608"], ["H05", "40595"], ["B23", "37395"], ["C09", "37353"], ["B29", "35652"], ["E04", "35644"], ["C12", "34769"], ["B41", "33654"], ["H03", "31350"], ["F02", "30083"], ["G05", "22665"], ["F24", "22263"], ["G09", "21974"], ["A23", "21695"], ["B62", "19324"], ["B32", "18949"], ["A63", "18427"], ["C23", "18069"], ["B21", "17969"], ["C04", "17721"], ["D06", "16419"], ["F04", "15917"], ["C01", "15725"], ["B05", "15693"], ["F01", "15097"], ["E21", "15006"], ["C22", "14756"], ["B22", "14622"], ["E02", "14451"], ["E05", "14053"], ["G07", "12006"], ["B25", "11954"], ["C10", "11951"], ["B66", "11786"], ["C02", "11718"], ["F23", "11559"], ["F25", "11521"], ["D01", "10307"], ["D21", "10271"], ["G08", "9850"], ["E06", "9805"], ["C11", "9786"], ["C03", "9399"], ["E01", "9284"], ["G10", "9089"], ["C21", "8314"], ["B24", "7946"], ["E03", "7733"], ["F21", "7659"], ["A45", "7616"], ["C25", "7427"], ["B26", "7160"], ["B28", "7105"], ["G21", "7092"], ["B63", "7070"], ["B42", "6644"], ["F28", "6260"], ["B27", "6094"], ["D04", "5852"], ["B61", "5668"], ["F27", "5422"], ["B64", "5324"], ["F15", "4903"], ["A41", "4614"], ["B08", "4516"], ["B30", "4496"], ["B43", "4434"], ["B02", "4372"], ["A62", "4319"], ["A43", "4278"], ["F41", "4186"], ["B67", "4098"], ["D03", "4023"], ["A44", "3932"], ["C30", "3876"], ["G04", "3750"], ["B44", "3602"], ["A21", "3498"], ["F42", "3488"], ["B03", "3383"], ["D05", "3284"], ["F26", "3213"], ["B07", "3135"], ["B31", "2954"]], "ipc3": [["A61K", "79536"], ["H01L", "65234"], ["G06F", "54396"], ["C07D", "47737"], ["H04N", "47605"], ["G01N", "43396"], ["G11B", "42397"], ["A61P", "41413"], ["C07C", "36004"], ["C08L", "31911"], ["B65D", "31543"], ["B29C", "31162"], ["G02B", "28083"], ["B01D", "27840"], ["H05K", "26124"], ["B01J", "25561"], ["G03G", "25538"], ["C12N", "23747"], ["C08G", "23155"], ["A61B", "20797"], ["B41J", "20593"], ["C07K", "20552"], ["B65H", "20486"], ["C08F", "20398"], ["B32B", "18924"], ["H04B", "18319"], ["C04B", "17703"], ["G01R", "17432"], ["H04L", "17122"], ["B65G", "17077"], ["H01R", "16158"], ["C08J", "16144"], ["A01N", "15975"], ["C08K", "15663"], ["C12P", "15522"], ["B60R", "14908"], ["H01J", "14696"], ["C09D", "14471"], ["G02F", "14317"], ["H04M", "14205"], ["F16L", "13973"], ["C23C", "13882"], ["G03B", "13586"], ["A61F", "13442"], ["H01H", "13357"], ["C09K", "13301"], ["A61M", "13085"], ["A23L", "13084"], ["B23K", "13059"], ["F16H", "12901"], ["G01B", "12439"], ["E04B", "12293"], ["B62D", "12199"], ["G06K", "11907"], ["C02F", "11621"], ["C12R", "11552"], ["H05B", "11441"], ["G06T", "11422"], ["F16K", "11361"], ["H03K", "10981"], ["H01F", "10925"], ["F02B", "10569"], ["C22C", "10308"], ["B23Q", "10297"], ["G09F", "10257"], ["H02K", "10206"], ["G05B", "10074"], ["C01B", "10069"], ["H01B", "10040"], ["F16D", "10028"], ["A61L", "9997"], ["G03F", "9896"], ["H04Q", "9736"], ["F16B", "9665"], ["C07B", "9602"], ["F02D", "9468"], ["B65B", "9434"], ["F24F", "9353"], ["G05D", "9288"], ["G11C", "9260"], ["B60K", "9126"], ["E06B", "9086"], ["B22D", "8866"], ["B29L", "8689"], ["C07F", "8528"], ["H01M", "8508"], ["B21D", "8466"], ["A01K", "8418"], ["A47J", "8230"], ["F02M", "8174"], ["H01S", "7992"], ["F16C", "7970"], ["B29K", "7933"], ["E21B", "7918"], ["B05B", "7818"], ["A61Q", "7691"], ["E04F", "7466"], ["F16F", "7463"], ["E04H", "7275"], ["A47B", "7130"]], "ipc4": [["A61K31", "44247"], ["H01L21", "41219"], ["H04N5", "20213"], ["G03G15", "19175"], ["H04N1", "16920"], ["G01N33", "16852"], ["C12N15", "14728"], ["C07K14", "14685"], ["A61K38", "14569"], ["G02F1", "13646"], ["H01L27", "12794"], ["A61K9", "12552"], ["B41J2", "11991"], ["H01L23", "11769"], ["C12R1", "11555"], ["H05K3", "11051"], ["G02B6", "11046"], ["G06F3", "10983"], ["G06F15", "10910"], ["H01L29", "10892"], ["G11B5", "10600"], ["G06F17", "10550"], ["C12P21", "9876"], ["C08K5", "9538"], ["G11B7", "9269"], ["H04N7", "8993"], ["G01N21", "8817"], ["C04B35", "8608"], ["G06F9", "8264"], ["A61K8", "8082"], ["B01D53", "8006"], ["A61P43", "7955"], ["G03F7", "7826"], ["G01R31", "7790"], ["C02F1", "7712"], ["C07B61", "7527"], ["B29C45", "7467"], ["A61K47", "7431"], ["H01R13", "7280"], ["B32B27", "7171"], ["G06F13", "7157"], ["A61P25", "7102"], ["A61P9", "6982"], ["G01N27", "6967"], ["A61K39", "6955"], ["E04B1", "6875"], ["H04L12", "6805"], ["A23L1", "6695"], ["H04N9", "6661"], ["A01N43", "6620"], ["C08J5", "6620"], ["A61B5", "6547"], ["H04B1", "6507"], ["C12N9", "6365"], ["G06F11", "6324"], ["H05K1", "6308"], ["A61P31", "6260"], ["G05B19", "6231"], ["C07D401", "6145"], ["C08L23", "6032"], ["C08G18", "6023"], ["C12N1", "5955"], ["C12Q1", "5918"], ["C08K3", "5905"], ["C09D5", "5894"], ["G06F12", "5738"], ["H04M1", "5666"], ["H04B7", "5626"], ["C07D405", "5506"], ["H01S3", "5503"], ["A61B17", "5414"], ["C12N5", "5262"], ["C07K16", "5243"], ["G11B15", "5165"], ["G03G21", "5087"], ["C08F2", "5068"], ["B65G47", "4996"], ["A61P37", "4893"], ["C07K1", "4833"], ["G11B20", "4759"], ["C11D3", "4645"], ["B41M5", "4584"], ["C09K3", "4580"], ["A61P35", "4565"], ["B29K105", "4542"], ["A61P29", "4327"], ["F16J15", "4237"], ["C07F9", "4194"], ["B01J23", "4122"], ["C07D213", "4115"], ["B29C47", "4087"], ["G06F1", "4069"], ["C07C69", "4015"], ["C07D417", "3979"], ["A61P3", "3954"], ["A61K7", "3911"], ["C07D403", "3883"], ["H05K7", "3874"], ["C07D409", "3866"], ["H04B10", "3771"]], "ipc5": [["A61K38/00", "11101"], ["G03G15/00", "8813"], ["A61P43/00", "8233"], ["C12N15/09", "8219"], ["C07B61/00", "7527"], ["A61P35/00", "5760"], ["C07K14/00", "5515"], ["A61K8/00", "4755"], ["G03G21/00", "4679"], ["A61K31/44", "4537"], ["A61P29/00", "4532"], ["C12P21/02", "4483"], ["H04N1/00", "4379"], ["A61K31/40", "4227"], ["H01L21/027", "3981"], ["A61K9/00", "3866"], ["A61K31/70", "3566"], ["H04B7/26", "3520"], ["G01N33/53", "3494"], ["C12N5/10", "3461"], ["G06T1/00", "3456"], ["A61K39/395", "3375"], ["H01L21/60", "3304"], ["H01L29/78", "3303"], ["A61K31/445", "3235"], ["A61K31/505", "3224"], ["A61K31/495", "3218"], ["C12R1/91", "3212"], ["G03G15/08", "3181"], ["H01L21/66", "3181"], ["G03G15/04", "3148"], ["C12P21/08", "3137"], ["C07D401/12", "3109"], ["A61P9/00", "3106"], ["A61P31/04", "3099"], ["C12Q1/68", "2996"], ["C07K16/00", "2993"], ["A61K39/00", "2992"], ["A61P9/10", "2962"], ["C12N1/21", "2932"], ["A61K31/415", "2912"], ["A61P31/12", "2846"], ["G02B6/00", "2814"], ["A61P9/12", "2811"], ["C08L101/00", "2811"], ["C08J5/18", "2804"], ["A61K31/00", "2766"], ["A61K31/55", "2749"], ["C07D405/12", "2567"], ["H01L27/04", "2539"], ["A61K31/47", "2529"], ["F02D45/00", "2521"], ["C07D471/04", "2510"], ["C08L83/04", "2499"], ["C07D487/04", "2362"], ["C12P21/00", "2353"], ["H01L21/205", "2350"], ["B01D53/34", "2347"], ["H04M11/00", "2312"], ["C08L67/00", "2310"], ["H01L21/822", "2289"], ["C12R1/19", "2284"], ["A61P25/00", "2283"], ["G06F15/16", "2283"], ["A61P25/04", "2275"], ["A61K31/435", "2259"], ["H05K3/34", "2258"], ["H04N5/225", "2253"], ["G06F17/50", "2242"], ["G06F13/00", "2224"], ["H01L21/30", "2222"], ["H04Q9/00", "2201"], ["A61K47/48", "2199"], ["A61P7/02", "2189"], ["G11B11/10", "2185"], ["A61P25/28", "2183"], ["C22C38/00", "2183"], ["H04N1/04", "2169"], ["A61P37/08", "2154"], ["G06F12/00", "2140"], ["H04N1/40", "2131"], ["G09F9/00", "2123"], ["A61P17/00", "2111"], ["C07D417/12", "2096"], ["H04N1/32", "2088"], ["H01S5/00", "2084"], ["C08F10/00", "2079"], ["A61K31/535", "2050"], ["A61P37/00", "2041"], ["C07D521/00", "2036"], ["H01L21/302", "2028"], ["G11B11/105", "2007"], ["G06F17/30", "1974"], ["A61K31/19", "1959"], ["H01L21/3205", "1929"], ["C12N15/12", "1926"], ["G06F17/21", "1921"], ["G01N33/543", "1918"], ["H01L23/50", "1906"], ["A61P11/00", "1905"]], "loc": [["21-01", "356"], ["26-05", "195"], ["09-05", "184"], ["09-03", "167"], ["09-01", "124"], ["14-03", "95"], ["11-02", "92"], ["07-01", "87"], ["19-06", "80"], ["03-01", "74"], ["02-04", "72"], ["06-01", "66"], ["19-08", "63"], ["10-01", "61"], ["13-03", "53"], ["07-02", "49"], ["25-01", "47"], ["20-03", "45"], ["24-02", "44"], ["08-07", "42"], ["12-11", "42"], ["02-05", "40"], ["06-04", "38"], ["23-04", "38"], ["23-01", "37"], ["05-06", "34"], ["02-02", "30"], ["14-01", "30"], ["06-06", "29"], ["28-03", "29"], ["06-13", "28"], ["14-99", "28"], ["08-05", "27"], ["15-99", "27"], ["10-07", "26"], ["08-08", "25"], ["23-03", "25"], ["04-01", "24"], ["06-09", "22"], ["10-04", "21"], ["06-07", "20"], ["07-04", "20"], ["06-03", "19"], ["02-07", "18"], ["03-03", "18"], ["21-02", "18"], ["26-04", "17"], ["07-06", "16"], ["07-99", "16"], ["26-02", "16"], ["02-03", "15"], ["15-09", "15"], ["19-01", "15"], ["19-07", "15"], ["23-02", "15"], ["08-03", "14"], ["22-06", "14"], ["25-02", "14"], ["27-05", "14"], ["11-01", "13"], ["15-02", "13"], ["07-05", "12"], ["09-02", "12"], ["09-07", "12"], ["06-10", "11"], ["07-07", "11"], ["10-05", "11"], ["12-08", "11"], ["14-02", "11"], ["15-05", "11"], ["15-06", "11"], ["19-99", "11"], ["21-03", "11"], ["08-06", "10"], ["15-07", "10"], ["19-04", "10"], ["05-05", "9"], ["06-08", "9"], ["08-01", "9"], ["19-02", "9"], ["24-01", "9"], ["01-01", "8"], ["16-01", "8"], ["16-06", "8"], ["19-03", "8"], ["01-02", "7"], ["07-03", "7"], ["08-99", "7"], ["10-02", "7"], ["12-12", "7"], ["12-16", "7"], ["25-03", "7"], ["08-09", "6"], ["11-03", "6"], ["28-02", "6"], ["02-01", "5"], ["06-05", "5"], ["09-09", "5"], ["12-05", "5"], ["13-02", "5"]]}