{"category": "1911", "countryCode": [["\u897f\u73ed\u7259", "es", "143"], ["\u6fb3\u5927\u5229\u4e9a", "au", "1"]], "legalStatus": [["\u672a\u77e5", "144"]], "applicationYear": [["1910", "144"]], "documentYear": [["1911", "144"]], "applicant": [["BRANDES AUGUST", "2"], ["CIE GENERALE DE CONSTRUCTION DE FOURS", "2"], ["FREUDENTHAL HEINRICH PETER CHRISTOPH", "2"], ["HELBRONNER ANDRE SAMSON SEBY", "2"], ["HENRI VICTOR", "2"], ["HEUSCH EDUARD HUGO", "2"], ["KRUPP AG", "2"], ["NEFF CARL", "2"], ["QUER BARTRAN MAGIN", "2"], ["RECKLINGHAUSEN MAX VON", "2"], ["SA DES FREINS UNIVERSELS POUR METIERS A TISSER", "2"], ["STUMPF JOHANN", "2"], ["VERDAGUER Y COMPANIA SOC EN COMANDITA", "2"], ["ACETYLENE DISSOUS & APLICATIONS DE LACETYLENE", "1"], ["ALARCON RUIZ SEBASTIAN", "1"], ["AMARE CODORNIU JUAN", "1"], ["ANTA MIRANDA JUAN DE", "1"], ["APOZNANSKI JOSEPH", "1"], ["ARMINAN COALLA CELESTINO", "1"], ["ARROYO DE UZURIAGA ANA", "1"], ["AYXELA JUVE JUAN", "1"], ["AZARA VICENTE JOSE MARIA", "1"], ["BAGUER VILA HERMENEGILDO", "1"], ["BAILLOU DE LA BROSSE JACQUES", "1"], ["BALIU Y MIRO", "1"], ["BARRIERE PROSPER", "1"], ["BASF AG", "1"], ["BATT HENRY", "1"], ["BBC BROWN BOVERI & CIE", "1"], ["BENET CABALLERO JUANA", "1"], ["BESSET ETIENNE", "1"], ["BIANCHI ZAFFOLI EMILIO", "1"], ["BOILER SCALERS LTD", "1"], ["BOLLO VITTORIO", "1"], ["BOTELLA PEREZ ADELAIDA", "1"], ["BOWMAN ELHANAM", "1"], ["BRAIBANT NESTOR", "1"], ["BROHMANN RUDOLF", "1"], ["CADENACCIO ETTORE", "1"], ["CASES PALMER DOMINGO", "1"], ["CASTELLO CARRERAS RAMON", "1"], ["CHARTRAND JEAN BAPTISTE", "1"], ["CIE POUR LA FABRICATION DES COMPTEURS ET MATERIEL DUSINES A GAZ", "1"], ["CLAESSEN CONRAD", "1"], ["CLEMENTS GEORGE FREDRICK", "1"], ["CORTAZAR MANUEL", "1"], ["CORTES HERMANOS", "1"], ["COTTON FRANK", "1"], ["CURT BERTHOLD MOELLER", "1"], ["DAY JOHN JACOB", "1"], ["DOBAO ISAAC", "1"], ["DOMINGO BADIELLAS JOSE", "1"], ["ESCUBOS FALGUERA JOSE", "1"], ["EUBOEOLITHWERKE A G OLTEN", "1"], ["FERNANDEZ PEREZ DEL RIO FRANCISCO", "1"], ["FIRST AMERICAN PERFUMERY OJA G M B H", "1"], ["FLADE GEORGE", "1"], ["FLO VALLS RAMON", "1"], ["FRANCAS TRAVERIA JOSE", "1"], ["GABARRO JULIEN RAMON", "1"], ["GABRIELLI CHARLES", "1"], ["GARNIER ALPHONSE EDOUARD", "1"], ["GIL RODRIGUEZ MIGUEL", "1"], ["GILMAN FRANK", "1"], ["GOMEZ GARCIA FRANCISCO", "1"], ["GONCELLA ANGELO", "1"], ["GONZALEZ RODRIGUEZ NAZARIO", "1"], ["GOTTARDO DE ANDREIS", "1"], ["GROSS HERMANOS", "1"], ["HABERMANN THEODOR", "1"], ["HARTMANN HUGO", "1"], ["HEIN REINOLD", "1"], ["HEIN RICHARD", "1"], ["HERRERA LUPION SALVADOR", "1"], ["HULOT HENRY", "1"], ["JACOB EDOUARD", "1"], ["JACQUET LOUIS PAUL CONSTANT JULES", "1"], ["JAFFO PAUL", "1"], ["JENNY THEODORE", "1"], ["JORDANA PEDRO", "1"], ["JOVER FERNANDEZ DE LIENCRES JOSE LUIS", "1"], ["KESTNER PAUL", "1"], ["KLIO WERK FABRIK FUER GEBRAUCHSGEGENSTAENDE G M B H", "1"], ["LA WASHINGTON S A", "1"], ["LAIR LIQUIDE", "1"], ["LATREILLE CLEDERE ADOLFO", "1"], ["LEDOUX HENRI BRUNO", "1"], ["LEIVA BRAVO JOAQUIN", "1"], ["LENTZ HUGO", "1"], ["LIEBICIN WERK FRITZ LIEBICH", "1"], ["LINSMEYER JOHANN ALEXANDER", "1"], ["LLOBET PASTORS JOAQUIN", "1"], ["LOEWENSTEIN FELIX", "1"], ["LOPEZ DE CEBALLOS AGUIRRE VENANCIO", "1"], ["LOPEZ MANTARAS VILLA GABRIEL", "1"], ["LOPEZ SERRANO JUAN JOSE", "1"], ["MAIGROT EUGENE", "1"], ["MAIZTEGUI IBARZABAL VALENTIN", "1"], ["MALIBRAN ALVARO DE", "1"], ["MANN & WILLKOMM A G", "1"]], "applicantCountryCode": [[null, "0"]], "inventor": [["CURT BERTHOLD MOELLER", "1"]], "ipc": [[null, "0"]], "ipc1": [[null, "0"]], "ipc2": [[null, "0"]], "ipc3": [[null, "0"]], "ipc4": [[null, "0"]], "ipc5": [[null, "0"]], "loc": [[null, "0"]]}