{"category": "1940", "countryCode": [["\u897f\u73ed\u7259", "es", "232"], ["\u82f1\u56fd", "gb", "77"], ["\u7231\u5c14\u5170", "ie", "1"]], "legalStatus": [["\u672a\u77e5", "310"]], "applicationYear": [["1939", "79"], ["1938", "229"], ["1937", "1"], ["1935", "1"]], "documentYear": [["1940", "310"]], "applicant": [["IG FARBENINDUSTRIE AG", "36"], ["DU PONT", "8"], ["ARMSTRONG CORK CO", "6"], ["INT LATEX PROCESSES LTD", "6"], ["ASS TELEPHONE & TELEGRAPH CO", "5"], ["PITTSBURGH PLATE GLASS CO", "4"], ["SIEMENS AG", "4"], ["STANDARD TELEPHONES CABLES LTD", "4"], ["BAITA PIERO", "3"], ["CIE POUR LA FABRICATION DES COMPTEURS ET MATERIEL DUSINES A GAZ", "3"], ["FIDES GES FUER DIE VERWALTUNG UND VERWERTUNG VON GEWERBLICHEN SCHUTZRECHTEN M B H", "3"], ["GEORGE HENRY CLIFFORD CORNER", "3"], ["LIGHTNING FASTENERS LTD", "3"], ["METALLGESELLSCHAFT AG", "3"], ["N V ORGANON", "3"], ["RICART MEDINA WIFREDO PELAYO", "3"], ["VIUDA E HIJOS DE DON JUAN DE LA CIERVA Y CODORNIU", "3"], ["AURIOL ANDRES AURIOL ALBERTO", "2"], ["BERGHAUS BERNHARD", "2"], ["CECIL RICHARD ALMAS CHADFIELD", "2"], ["DUISBURGER KUPFERHUETTE", "2"], ["DURAND & HUGHENIN A G", "2"], ["ELECTRICITAETS GES SANITAS MIT BESCHRAENKTER HAFTUNG", "2"], ["FLII ORSENIGO S A", "2"], ["GEORGE WILLIAM JOHNSON", "2"], ["JUSTIN ERWIN POLLAK", "2"], ["KNOLL A G CHEMISCHEFABRIKEN", "2"], ["KORESKA WILHELM", "2"], ["MARCONIS WIRELESS TELEGRAPH COMPANY LTD", "2"], ["MIJ EXPLOITATIE OCTROOIEN NV", "2"], ["N V DE BATAAFSCHE PETROLEUM MIJ", "2"], ["N V NIEUWE OCTROOI MIJ", "2"], ["OESTERREICHISCHE AGA WERKE A G", "2"], ["PIRELLI", "2"], ["SCHNEIDER & CIE", "2"], ["SER SA", "2"], ["SOC DETUDES ET APPLICATIONS INDUSTRIELLES", "2"], ["SOC GEN METALLURGIQUE DE HOBOKEN S A", "2"], ["SOLVAY", "2"], ["VER DEUTSCHE METALLWERKE AG", "2"], ["VER GLUEHLAMPEN UND ELECTRICITAETS A G", "2"], ["A B GERH AREHNS MEKANISKA VERKST", "1"], ["AEG", "1"], ["AG FUER TECHNISCHE STUDIEN", "1"], ["ALAN JOHN MELVILLE HIPWELL", "1"], ["ALBERT LASCH", "1"], ["ALBERT PRODUCTS LTD", "1"], ["ALEXANDER JOSEFOWITSCH LOGUIN", "1"], ["ALEXANDER PAUL", "1"], ["ALFA ROMEO S A", "1"], ["ALFRED EMILE PHILLIPPS", "1"], ["ALFRED SYDNEY RAYMOND", "1"], ["ALLIAGES AUTOPROTEGES S A", "1"], ["ANGULO ALVAREZ ANTONIO", "1"], ["ANTON MARCO JOSE CARLOS", "1"], ["ARADO FLUGZEUGWERKE GMBH", "1"], ["ARDELTWERKE GMBH", "1"], ["ARTHUR HADDON", "1"], ["ARTHUR POWELL", "1"], ["ARTHUR SAM CHESTON", "1"], ["ASBORNO GIOVANNI BATTISTA", "1"], ["ASBORNO NATALE", "1"], ["ASSUR GJESSING OPPEGAARD", "1"], ["ASTECK CALLERY EMIR HASSAN ALOYSIUS D", "1"], ["AURIOL ALBERTO", "1"], ["AURIOL ANDRES", "1"], ["BAIRD TELEVISION LTD", "1"], ["BAKER PERKINS LTD", "1"], ["BARMER MASCHF A G", "1"], ["BASLER HERMANN", "1"], ["BENDIX AVIAT CORP", "1"], ["BENGOECHEA JUSTE Y COMPANIA LTDA", "1"], ["BERKEL AUTO SCALE CO LTD", "1"], ["BERMUDEZ JULIAN", "1"], ["BERNARD GOUGH HARRISON", "1"], ["BERNSTEIN KURT", "1"], ["BONORA MUNOZ ALEJANDRO", "1"], ["BOTTARO ANTONIO", "1"], ["BRAND JOSEF", "1"], ["BRINK HANS OTTO", "1"], ["BRITISH COTTON IND RES ASSOC", "1"], ["BRITISH THOMSON HOUSTON CO LTD", "1"], ["BRITISH TITAN PRODUCTS", "1"], ["BRODY IMRE", "1"], ["BROMSREGULATOR SVENSKA AB", "1"], ["BUSS AG", "1"], ["BUTTNER WERKE A G", "1"], ["C LORENZ AG", "1"], ["CABLE & WIRELESS LTD", "1"], ["CAMON CANO JESUS", "1"], ["CARLIER JOSEPH", "1"], ["CARRING CARL ALGOT", "1"], ["CASPARY EMIL", "1"], ["CASTELLI XAVIER FRANCOIS", "1"], ["CASTIGLIONI GIUSEPPE", "1"], ["CECIL WILLIAM PARSONS", "1"], ["CELLONA", "1"], ["CHARLES JAMES STOPFORD", "1"], ["CHARLES TAGLIABUE MFG CO", "1"], ["CHARLES WEIZMANN", "1"]], "applicantCountryCode": [["\u5fb7\u56fd", "14"], ["\u6bd4\u5229\u65f6", "3"], ["\u610f\u5927\u5229", "3"], ["\u8377\u5170", "3"], ["\u7f8e\u56fd", "3"], ["\u5965\u5730\u5229", "1"], ["\u6377\u514b\u65af\u6d1b\u4f10\u514b", "1"], ["\u897f\u73ed\u7259", "1"], ["\u82f1\u56fd", "1"]], "inventor": [[null, "0"]], "ipc": [["H04M15/04", "7"], ["H04Q3/00", "7"], ["H04Q3/42", "7"], ["C22A", "3"], ["D06A", "3"], ["F41A", "3"], ["B29D5/02", "2"], ["C03A", "2"], ["C07C1/06", "2"], ["C09A", "2"], ["D01A", "2"], ["D03A", "2"], ["H01A", "2"], ["A01G3/06", "1"], ["A23J1/14", "1"], ["A23J3/20", "1"], ["A41F1/00", "1"], ["A44C11/02", "1"], ["A45D4/12", "1"], ["A47D1/10", "1"], ["A47H15/02", "1"], ["A47L11/12", "1"], ["A61G7/05", "1"], ["A62A", "1"], ["A63B61/04", "1"], ["B01F5/04", "1"], ["B02C17/00", "1"], ["B02C17/06", "1"], ["B02C17/18", "1"], ["B05B3/04", "1"], ["B21C23/01", "1"], ["B22A", "1"], ["B23K35/36", "1"], ["B23Q5/26", "1"], ["B27K3/32", "1"], ["B28B13/02", "1"], ["B30A", "1"], ["B30B11/02", "1"], ["B30B15/30", "1"], ["B41J3/24", "1"], ["B41J35/22", "1"], ["B43K1/01", "1"], ["B60B33/06", "1"], ["B60C17/00", "1"], ["B60J3/02", "1"], ["B65D", "1"], ["C02A", "1"], ["C02F3/04", "1"], ["C07A", "1"], ["C07C1/24", "1"], ["C07D209/44", "1"], ["C08B1/14", "1"], ["C08F244/00", "1"], ["C08G8/28", "1"], ["C08L23/22", "1"], ["C08L61/06", "1"], ["C09B1/48", "1"], ["C09C1/36", "1"], ["C10B3/00", "1"], ["C10M133/18", "1"], ["C10M141/10", "1"], ["C22B26/22", "1"], ["C22C9/01", "1"], ["C23A", "1"], ["D04D5/00", "1"], ["D06M17/00", "1"], ["D06N3/00", "1"], ["D06N3/06", "1"], ["D21J7/00", "1"], ["E01A", "1"], ["E04A", "1"], ["E04F15/12", "1"], ["E05C17/34", "1"], ["F02A", "1"], ["F21V7/04", "1"], ["F24F3/16", "1"], ["F25B41/00", "1"], ["F25B43/00", "1"], ["F41A19/30", "1"], ["F41A3/26", "1"], ["F41A3/32", "1"], ["F41A3/82", "1"], ["F41A5/18", "1"], ["F41A9/76", "1"], ["F41G3/06", "1"], ["F42B14/02", "1"], ["G01C1/10", "1"], ["G01D9/16", "1"], ["G01G23/20", "1"], ["G01N11/14", "1"], ["G01N27/04", "1"], ["G01R23/00", "1"], ["G03B9/58", "1"], ["G05B19/10", "1"], ["G05D3/14", "1"], ["H01H23/16", "1"], ["H01H51/32", "1"], ["H01J1/16", "1"], ["H01J31/12", "1"], ["H01M12/06", "1"]], "ipc1": [["C", "23"], ["H", "21"], ["B", "18"], ["A", "11"], ["D", "11"], ["F", "10"], ["G", "9"], ["E", "4"]], "ipc2": [["H04", "9"], ["H01", "7"], ["G01", "6"], ["C07", "5"], ["C22", "5"], ["D06", "5"], ["F41", "5"], ["C09", "4"], ["A47", "3"], ["B60", "3"], ["A23", "2"], ["B23", "2"], ["B29", "2"], ["B30", "2"], ["C02", "2"], ["C03", "2"], ["C08", "2"], ["C10", "2"], ["D01", "2"], ["D03", "2"], ["E04", "2"], ["G05", "2"], ["H03", "2"], ["H05", "2"], ["A01", "1"], ["A41", "1"], ["A44", "1"], ["A45", "1"], ["A61", "1"], ["A62", "1"], ["A63", "1"], ["B01", "1"], ["B02", "1"], ["B05", "1"], ["B21", "1"], ["B22", "1"], ["B27", "1"], ["B28", "1"], ["B41", "1"], ["B43", "1"], ["B65", "1"], ["C23", "1"], ["D04", "1"], ["D21", "1"], ["E01", "1"], ["E05", "1"], ["F02", "1"], ["F21", "1"], ["F24", "1"], ["F25", "1"], ["F42", "1"], ["G03", "1"], ["H02", "1"]], "ipc3": [["H04M", "7"], ["H04Q", "7"], ["F41A", "4"], ["C07C", "3"], ["C22A", "3"], ["D06A", "3"], ["A23J", "2"], ["B29D", "2"], ["C03A", "2"], ["C09A", "2"], ["D01A", "2"], ["D03A", "2"], ["D06N", "2"], ["G01N", "2"], ["H01A", "2"], ["H01H", "2"], ["H01J", "2"], ["A01G", "1"], ["A41F", "1"], ["A44C", "1"], ["A45D", "1"], ["A47D", "1"], ["A47H", "1"], ["A47L", "1"], ["A61G", "1"], ["A62A", "1"], ["A63B", "1"], ["B01F", "1"], ["B02C", "1"], ["B05B", "1"], ["B21C", "1"], ["B22A", "1"], ["B23K", "1"], ["B23Q", "1"], ["B27K", "1"], ["B28B", "1"], ["B30A", "1"], ["B30B", "1"], ["B41J", "1"], ["B43K", "1"], ["B60B", "1"], ["B60C", "1"], ["B60J", "1"], ["B65D", "1"], ["C02A", "1"], ["C02F", "1"], ["C07A", "1"], ["C07D", "1"], ["C08B", "1"], ["C08F", "1"], ["C08G", "1"], ["C08L", "1"], ["C09B", "1"], ["C09C", "1"], ["C10B", "1"], ["C10M", "1"], ["C22B", "1"], ["C22C", "1"], ["C23A", "1"], ["D04D", "1"], ["D06M", "1"], ["D21J", "1"], ["E01A", "1"], ["E04A", "1"], ["E04F", "1"], ["E05C", "1"], ["F02A", "1"], ["F21V", "1"], ["F24F", "1"], ["F25B", "1"], ["F41G", "1"], ["F42B", "1"], ["G01C", "1"], ["G01D", "1"], ["G01G", "1"], ["G01R", "1"], ["G03B", "1"], ["G05B", "1"], ["G05D", "1"], ["H01M", "1"], ["H01R", "1"], ["H02N", "1"], ["H03J", "1"], ["H03K", "1"], ["H04J", "1"], ["H04L", "1"], ["H05B", "1"], ["H05F", "1"]], "ipc4": [["H04M15", "7"], ["H04Q3", "7"], ["C07C1", "3"], ["B29D5", "2"], ["D06N3", "2"], ["A01G3", "1"], ["A23J1", "1"], ["A23J3", "1"], ["A41F1", "1"], ["A44C11", "1"], ["A45D4", "1"], ["A47D1", "1"], ["A47H15", "1"], ["A47L11", "1"], ["A61G7", "1"], ["A63B61", "1"], ["B01F5", "1"], ["B02C17", "1"], ["B05B3", "1"], ["B21C23", "1"], ["B23K35", "1"], ["B23Q5", "1"], ["B27K3", "1"], ["B28B13", "1"], ["B30B11", "1"], ["B30B15", "1"], ["B41J3", "1"], ["B41J35", "1"], ["B43K1", "1"], ["B60B33", "1"], ["B60C17", "1"], ["B60J3", "1"], ["C02F3", "1"], ["C07D209", "1"], ["C08B1", "1"], ["C08F244", "1"], ["C08G8", "1"], ["C08L23", "1"], ["C08L61", "1"], ["C09B1", "1"], ["C09C1", "1"], ["C10B3", "1"], ["C10M133", "1"], ["C10M141", "1"], ["C22B26", "1"], ["C22C9", "1"], ["D04D5", "1"], ["D06M17", "1"], ["D21J7", "1"], ["E04F15", "1"], ["E05C17", "1"], ["F21V7", "1"], ["F24F3", "1"], ["F25B41", "1"], ["F25B43", "1"], ["F41A19", "1"], ["F41A3", "1"], ["F41A5", "1"], ["F41A9", "1"], ["F41G3", "1"], ["F42B14", "1"], ["G01C1", "1"], ["G01D9", "1"], ["G01G23", "1"], ["G01N11", "1"], ["G01N27", "1"], ["G01R23", "1"], ["G03B9", "1"], ["G05B19", "1"], ["G05D3", "1"], ["H01H23", "1"], ["H01H51", "1"], ["H01J1", "1"], ["H01J31", "1"], ["H01M12", "1"], ["H01M4", "1"], ["H01M6", "1"], ["H01R33", "1"], ["H02N1", "1"], ["H03J5", "1"], ["H03K4", "1"], ["H04J3", "1"], ["H04L13", "1"], ["H04L15", "1"], ["H05B3", "1"], ["H05F3", "1"]], "ipc5": [["H04M15/04", "7"], ["H04Q3/00", "7"], ["H04Q3/42", "7"], ["B29D5/02", "2"], ["C07C1/06", "2"], ["A01G3/06", "1"], ["A23J1/14", "1"], ["A23J3/20", "1"], ["A41F1/00", "1"], ["A44C11/02", "1"], ["A45D4/12", "1"], ["A47D1/10", "1"], ["A47H15/02", "1"], ["A47L11/12", "1"], ["A61G7/05", "1"], ["A63B61/04", "1"], ["B01F5/04", "1"], ["B02C17/00", "1"], ["B02C17/06", "1"], ["B02C17/18", "1"], ["B05B3/04", "1"], ["B21C23/01", "1"], ["B23K35/36", "1"], ["B23Q5/26", "1"], ["B27K3/32", "1"], ["B28B13/02", "1"], ["B30B11/02", "1"], ["B30B15/30", "1"], ["B41J3/24", "1"], ["B41J35/22", "1"], ["B43K1/01", "1"], ["B60B33/06", "1"], ["B60C17/00", "1"], ["B60J3/02", "1"], ["C02F3/04", "1"], ["C07C1/24", "1"], ["C07D209/44", "1"], ["C08B1/14", "1"], ["C08F244/00", "1"], ["C08G8/28", "1"], ["C08L23/22", "1"], ["C08L61/06", "1"], ["C09B1/48", "1"], ["C09C1/36", "1"], ["C10B3/00", "1"], ["C10M133/18", "1"], ["C10M141/10", "1"], ["C22B26/22", "1"], ["C22C9/01", "1"], ["D04D5/00", "1"], ["D06M17/00", "1"], ["D06N3/00", "1"], ["D06N3/06", "1"], ["D21J7/00", "1"], ["E04F15/12", "1"], ["E05C17/34", "1"], ["F21V7/04", "1"], ["F24F3/16", "1"], ["F25B41/00", "1"], ["F25B43/00", "1"], ["F41A19/30", "1"], ["F41A3/26", "1"], ["F41A3/32", "1"], ["F41A3/82", "1"], ["F41A5/18", "1"], ["F41A9/76", "1"], ["F41G3/06", "1"], ["F42B14/02", "1"], ["G01C1/10", "1"], ["G01D9/16", "1"], ["G01G23/20", "1"], ["G01N11/14", "1"], ["G01N27/04", "1"], ["G01R23/00", "1"], ["G03B9/58", "1"], ["G05B19/10", "1"], ["G05D3/14", "1"], ["H01H23/16", "1"], ["H01H51/32", "1"], ["H01J1/16", "1"], ["H01J31/12", "1"], ["H01M12/06", "1"], ["H01M4/36", "1"], ["H01M6/22", "1"], ["H01R33/97", "1"], ["H02N1/08", "1"], ["H03J5/00", "1"], ["H03K4/16", "1"], ["H03K4/34", "1"], ["H04J3/04", "1"], ["H04L13/10", "1"], ["H04L15/34", "1"], ["H05B3/68", "1"], ["H05F3/04", "1"]], "loc": [[null, "0"]]}