{"category": "1952", "countryCode": [["\u7f8e\u56fd", "us", "1013"], ["\u897f\u73ed\u7259", "es", "433"], ["\u52a0\u62ff\u5927", "ca", "206"], ["\u7231\u5c14\u5170", "ie", "1"]], "legalStatus": [["\u5931\u6548\u4e13\u5229", "956"], ["\u672a\u77e5", "697"]], "applicationYear": [["1951", "453"], ["1950", "170"], ["1949", "240"], ["1948", "222"], ["1947", "168"], ["1946", "105"], ["1945", "59"], ["1944", "9"], ["1943", "5"], ["1942", "3"], ["1941", "2"], ["1940", "1"]], "documentYear": [["1952", "1653"]], "applicant": [["STANDARD OIL DEV CO", "27"], ["WESTERN ELECTRIC CO", "15"], ["BELL TELEPHONE LABOR INC", "13"], ["GEN ELECTRIC", "13"], ["IBM", "12"], ["RCA CORP", "11"], ["BENDIX AVIAT CORP", "10"], ["GEN MOTORS CORP", "10"], ["RAYTHEON MFG CO", "9"], ["COLLINS RADIO CO", "7"], ["DU PONT", "7"], ["GEN ELECTRIC CANADA", "7"], ["AMERICAN CYANAMID CO", "6"], ["ELECTROLUX AB", "6"], ["MANUFACTURAS MET\u00c1LICAS MADRILE AS S A", "6"], ["MONSANTO CHEMICALS", "6"], ["PHILIPS NV", "6"], ["ROSANAS GIRBAU MAR\u00cdA", "6"], ["CHRYSLER CORP", "5"], ["ECUSTA PAPER CORP", "5"], ["ALLIS CHALMERS MFG CO", "4"], ["AMERICAN OPTICAL CORP", "4"], ["AMERICAN STEEL FOUNDRIES", "4"], ["CERDA CONST MEC", "4"], ["ELECTROLUX CORP", "4"], ["JOACHIM KOLBE", "4"], ["TEXAS CO", "4"], ["ABBOTT LAB", "3"], ["ARMCO STEEL CORP", "3"], ["AUTOMATIC ELECT LAB", "3"], ["BALDWIN CO", "3"], ["BRIGGS MFG CO", "3"], ["DURAN MARTINEZ ERNESTO", "3"], ["EX CELL O CORP", "3"], ["FORMOSO SIABA V\u00cdCTOR", "3"], ["FOSTER WHEELER CORP", "3"], ["GEN ANILINE & FILM CORP", "3"], ["GRAU ESTANY RAM\u00d3N", "3"], ["GRAY GEORGE F", "3"], ["HOOVER CO", "3"], ["INFILCO INC", "3"], ["KAUTO S L", "3"], ["MARCONI CO CANADA", "3"], ["PRATT VERNEUR E", "3"], ["RODR\u00cdGUEZ P\u00c9REZ ANDR\u00c9S", "3"], ["SOCONY VACUUM OIL CO INC", "3"], ["SPECIALTIES DEV CORP", "3"], ["VILLAREAL REZUSTA NARCISO", "3"], ["WOMEN SAM SAM", "3"], ["AIR LIQUIDE", "2"], ["AIR REDUCTION", "2"], ["AISCONDEL SA", "2"], ["AMERICAN CAN CO", "2"], ["AMERICAN GAS ASS", "2"], ["AMERICAN STEEL & WIRE CO", "2"], ["AMERICAN VISCOSE CORP", "2"], ["ASCONDEL S A", "2"], ["AUSTIN MOTOR CO LTD", "2"], ["BENITO DELGADO Y L\u00d3PEZ FRANCISCO", "2"], ["BEUTER SWISSIG GUILLERMO", "2"], ["BOCJL CORP", "2"], ["BORT FERRIS VICENTE", "2"], ["BRENNAN JOSEPH B", "2"], ["BRYANT GRINDER CORP", "2"], ["BUSQUETS CASANOVAS CASIMIRO", "2"], ["BUXEDA BOSCH TOM\u00c1S", "2"], ["CAMILLE DREYFUS", "2"], ["CARNIC\u00c9 FERR\u00c9S JUAN", "2"], ["CECIL CLERK ROBERT", "2"], ["CELANESE CORP", "2"], ["COLONIAL INSULATOR COMPANY", "2"], ["COM AN\u00d3NIMA BULTO", "2"], ["COMB ENG SUPERHEATER INC", "2"], ["CONSTRUCCIONES MEC\u00c1MICAS CERD\u00c1NS S A", "2"], ["COUCHOT ORVILLE F", "2"], ["CSF", "2"], ["CUTTER CRAVAT INC", "2"], ["DAVID SAMIRAN", "2"], ["DECKEL FRIEDRICH W", "2"], ["DECKEL HANS", "2"], ["FLEGENHEIMER GAST\u00d3N", "2"], ["FREDERICKS WILLIAM M", "2"], ["GEN RAILWAY SIGNAL CO", "2"], ["GONZALEZ COSTAL ISAAC", "2"], ["GOODRICH CO B F", "2"], ["GREGOR FRANK J", "2"], ["H Y BASSETT", "2"], ["HONEYWELL REGULATOR CO", "2"], ["HONORARY ADVISORY COUNCIL SCI", "2"], ["HOUDRY PROCESS CORP", "2"], ["HUMPHREYS & GLASGOW LTD", "2"], ["KELLOGG M W CO", "2"], ["KRUFT HEINROCH", "2"], ["KUHN DE LA ESCOSURA CARLOS", "2"], ["LIONEL CORP", "2"], ["L\u00d3PEZ BRIBIAN JOS\u00c9", "2"], ["MART\u00cdNELL MORERA FRANCISCO", "2"], ["MENSA ORDETX FRANCISCO DE PADUA", "2"], ["MERCK & CO INC", "2"], ["NAT ALUMINATE CORP", "2"]], "applicantCountryCode": [["\u897f\u73ed\u7259", "94"], ["\u7f8e\u56fd", "8"], ["\u5fb7\u56fd", "6"], ["\u8377\u5170", "6"], ["\u6cd5\u56fd", "4"], ["\u963f\u6839\u5ef7", "1"], ["\u5965\u5730\u5229", "1"], ["\u82f1\u56fd", "1"], ["\u5217\u652f\u6566\u58eb\u767b", "1"]], "inventor": [["GEORG KOGEL WILHELM", "4"], ["JOACHIM KOLBE", "4"], ["KLEMPERER HANS", "4"], ["BANKER OSCAR H", "3"], ["BERGGREN GEORGE E", "3"], ["DAWSON JOHN W", "3"], ["Edward L. Verhagen", "3"], ["Florence C. Witmer", "3"], ["GRAY GEORGE F", "3"], ["Jack Orloff", "3"], ["PRATT VERNEUR E", "3"], ["WINKLER ALBERT H", "3"], ["WOMEN SAM SAM", "3"], ["BONANNO JOSEPH L", "2"], ["BRENNAN JOSEPH B", "2"], ["CECIL CLERK ROBERT", "2"], ["CHUTE WALTER JOHN", "2"], ["COUCHOT ORVILLE F", "2"], ["DAVID SAMIRAN", "2"], ["DICKINSON ARTHUR H", "2"], ["DOELZ MELVIN L", "2"], ["DOMENICK PAPA", "2"], ["DOUGHMAN FERMAN C", "2"], ["ELLIS JOHN L", "2"], ["EMERSON WILLIAM S", "2"], ["EMIL CARLSON", "2"], ["ERIK WIDELL NILS", "2"], ["ERWIN SCHWENK", "2"], ["FEILD ALEXANDER L", "2"], ["FRAYNE JOHN G", "2"], ["FREDERICKS WILLIAM M", "2"], ["FRENTZEL HERMAN C", "2"], ["GANZ RUDOLPH V", "2"], ["GILLE WILLIS H", "2"], ["GOETZEL CLAUS G", "2"], ["GRAHAM ROBERT E", "2"], ["GREGOR FRANK J", "2"], ["HALL EDWIN L", "2"], ["JACOBY ARTHUR L", "2"], ["JOHN STUDENY", "2"], ["KNOBLAUGH ARMAND F", "2"], ["KOLFENBACH JOHN J", "2"], ["LANG JOSEPH C", "2"], ["LEVY ROBERT M", "2"], ["MARKS HENRY C", "2"], ["MCKEE ROBERT C", "2"], ["MORWAY ARNOLD J", "2"], ["NEWMAN MELVIN S", "2"], ["ODELL WILLIAM W", "2"], ["PERCY SAUNDERS ALFRED", "2"], ["REILLY JR GEORGE W", "2"], ["SCHUR MILTON O", "2"], ["SPOONER JR DAVID C", "2"], ["WALSH JR DAVID C", "2"], ["WEST ERNEST", "2"], ["WEST FREDERICK JOSEPH", "2"], ["WRIGHT GEORGE F", "2"], ["ABEEL JR ALAN C", "1"], ["ABRAHAM EDELMAN", "1"], ["ABRAHAM SLOAN", "1"], ["ACHENBACH JOHN C", "1"], ["ADAMIR MARCHAND", "1"], ["ADAMS GEORGE P", "1"], ["ADAMS HAROLD B", "1"], ["ADAMS JOHN M", "1"], ["ADOLPH WAHLE", "1"], ["AGNEW WILLIAM YOUNG", "1"], ["AIME GODMAIRE", "1"], ["ALDEN BLAIR S", "1"], ["ALDEN FRANK S", "1"], ["ALDERSON SAMUEL W", "1"], ["ALDO BALMA", "1"], ["ALEX KEHM", "1"], ["ALEXANDER WARREN A", "1"], ["ALEXANDER WOLF", "1"], ["ALLAN GLAZER", "1"], ["ALLEN ADDA M", "1"], ["ALLEN BLOOM", "1"], ["ALLEN FREDERICK", "1"], ["ALLEN HAROLD P", "1"], ["ALLEN HOWARD B JR", "1"], ["ALLIENNE VALERE GAETAN ROBERT", "1"], ["ANDERSON EARL I", "1"], ["ANDERSON EDWIN E", "1"], ["ANDERSON FRANK P", "1"], ["ANDERSON HOMER G", "1"], ["ANDERSON JAMES L", "1"], ["ANDERSON MYRTLE M", "1"], ["ANDERSON RAYMOND L", "1"], ["ANDRE DANZIN", "1"], ["ANDREW CARL L", "1"], ["ANDREW KALITINSKY", "1"], ["ANGUS LOVE", "1"], ["ANNA WHITTAKER", "1"], ["ANNE ESCHER", "1"], ["ANTHONY WINTHER", "1"], ["APKER LEROY", "1"], ["ARCHIBALD FRANCIS M", "1"], ["ARCHIE JR BENNIE LEE", "1"], ["ARMS MERTON H", "1"]], "ipc": [["D03A", "8"], ["A01A", "7"], ["F16A", "7"], ["B01A", "6"], ["B65A", "6"], ["D01A", "5"], ["D06A", "5"], ["A23A", "4"], ["A47L9/10", "4"], ["B29C35/06", "4"], ["B29C47/00", "4"], ["B60G21/05", "4"], ["B62A", "4"], ["F02A", "4"], ["F27A", "4"], ["H01F21/06", "4"], ["A41F1/00", "3"], ["A45C11/32", "3"], ["A45D29/00", "3"], ["A61A", "3"], ["A62C13/00", "3"], ["B27A", "3"], ["B28A", "3"], ["B62D49/06", "3"], ["B65H35/00", "3"], ["C07A", "3"], ["F42A", "3"], ["H04A", "3"], ["A01K89/06", "2"], ["A01K93/00", "2"], ["A01K97/06", "2"], ["A44A", "2"], ["A44C5/20", "2"], ["A47D1/10", "2"], ["A47K5/10", "2"], ["A47L9/28", "2"], ["A63A", "2"], ["B01B1/04", "2"], ["B01J21/00", "2"], ["B01J21/12", "2"], ["B01J37/02", "2"], ["B01J8/32", "2"], ["B05B15/02", "2"], ["B23B47/34", "2"], ["B25B21/02", "2"], ["B29C51/18", "2"], ["B29C65/48", "2"], ["B41D5/00", "2"], ["B42D15/08", "2"], ["B43K24/08", "2"], ["B60C25/02", "2"], ["B60G3/26", "2"], ["B60J3/00", "2"], ["B60J7/12", "2"], ["B60T11/224", "2"], ["B61D19/00", "2"], ["B61L1/20", "2"], ["C02F1/72", "2"], ["C02F1/76", "2"], ["C04A", "2"], ["C07C43/14", "2"], ["C09A", "2"], ["C09J189/00", "2"], ["C10G9/38", "2"], ["C23F11/14", "2"], ["D04A", "2"], ["D04B15/54", "2"], ["E04B", "2"], ["E06B3/44", "2"], ["E06B7/084", "2"], ["F01L1/25", "2"], ["F16B21/16", "2"], ["F16B37/02", "2"], ["F16D7/04", "2"], ["F16K31/20", "2"], ["F24F3/14", "2"], ["F25A", "2"], ["F25B33/00", "2"], ["F25B41/00", "2"], ["G01A", "2"], ["G01G19/64", "2"], ["G01G23/365", "2"], ["G01R21/00", "2"], ["G04B19/253", "2"], ["G06G3/00", "2"], ["G07F9/06", "2"], ["G10C3/16", "2"], ["H01A", "2"], ["H01Q1/10", "2"], ["A01B23/06", "1"], ["A01B35/02", "1"], ["A01B39/18", "1"], ["A01B49/04", "1"], ["A01B51/02", "1"], ["A01B63/10", "1"], ["A01B63/32", "1"], ["A01C23/04", "1"], ["A01C3/06", "1"], ["A01C7/18", "1"], ["A01D25/04", "1"]], "ipc1": [["B", "278"], ["A", "194"], ["F", "181"], ["C", "130"], ["G", "116"], ["H", "98"], ["E", "70"], ["D", "63"]], "ipc2": [["F16", "67"], ["G01", "58"], ["A47", "48"], ["H01", "46"], ["B65", "45"], ["A01", "43"], ["C07", "41"], ["B01", "34"], ["B60", "34"], ["H04", "28"], ["A61", "26"], ["F02", "23"], ["C08", "21"], ["B23", "19"], ["A63", "17"], ["C09", "17"], ["H03", "17"], ["C10", "16"], ["D06", "16"], ["E04", "16"], ["F24", "16"], ["F25", "16"], ["A45", "15"], ["B29", "14"], ["B62", "14"], ["E05", "14"], ["E21", "14"], ["F23", "14"], ["B24", "13"], ["C23", "13"], ["E06", "13"], ["D01", "12"], ["D04", "12"], ["H02", "12"], ["B41", "11"], ["B61", "11"], ["B66", "11"], ["D03", "11"], ["B25", "10"], ["B64", "10"], ["A41", "9"], ["G03", "9"], ["G05", "9"], ["G07", "9"], ["A24", "8"], ["F01", "8"], ["A23", "7"], ["F04", "7"], ["F41", "7"], ["F42", "7"], ["G06", "7"], ["A62", "6"], ["B27", "6"], ["C02", "6"], ["E02", "6"], ["E03", "6"], ["G04", "6"], ["G09", "6"], ["A43", "5"], ["A44", "5"], ["B05", "5"], ["B28", "5"], ["B67", "5"], ["C04", "5"], ["D05", "5"], ["D21", "5"], ["F28", "5"], ["B22", "4"], ["B26", "4"], ["B31", "4"], ["B42", "4"], ["C03", "4"], ["F15", "4"], ["F21", "4"], ["F27", "4"], ["G02", "4"], ["G10", "4"], ["G11", "4"], ["A21", "3"], ["A22", "3"], ["B02", "3"], ["B21", "3"], ["B63", "3"], ["C01", "3"], ["C11", "3"], ["C21", "3"], ["C25", "3"], ["G08", "3"], ["B06", "2"], ["B07", "2"], ["B30", "2"], ["B43", "2"], ["B44", "2"], ["C22", "2"], ["D02", "2"], ["E01", "2"], ["F17", "2"], ["F22", "2"], ["H05", "2"], ["A42", "1"]], "ipc3": [["C07C", "26"], ["G01B", "16"], ["A01K", "14"], ["B01J", "14"], ["B65D", "14"], ["F16H", "13"], ["A47L", "12"], ["B29C", "12"], ["E21B", "12"], ["B24B", "11"], ["F25B", "11"], ["G01R", "11"], ["B01D", "10"], ["B65H", "10"], ["E06B", "10"], ["F16B", "10"], ["H01H", "10"], ["C08F", "9"], ["C10G", "9"], ["D04B", "9"], ["H03K", "9"], ["B62D", "8"], ["C07D", "8"], ["D03A", "8"], ["F16D", "8"], ["G03B", "8"], ["A01A", "7"], ["A45C", "7"], ["A45D", "7"], ["A47G", "7"], ["A47J", "7"], ["A47K", "7"], ["B65B", "7"], ["B65G", "7"], ["E05B", "7"], ["F16A", "7"], ["G07F", "7"], ["H01J", "7"], ["A01B", "6"], ["A24F", "6"], ["A47B", "6"], ["A62C", "6"], ["B01A", "6"], ["B23K", "6"], ["B60G", "6"], ["B64C", "6"], ["B65A", "6"], ["C02F", "6"], ["C08K", "6"], ["C23C", "6"], ["E04H", "6"], ["F16K", "6"], ["G01V", "6"], ["H01F", "6"], ["H01Q", "6"], ["H04N", "6"], ["A01D", "5"], ["B23Q", "5"], ["B25B", "5"], ["B60C", "5"], ["B60S", "5"], ["B61D", "5"], ["C09D", "5"], ["D01A", "5"], ["D06A", "5"], ["E04G", "5"], ["F02M", "5"], ["F16L", "5"], ["F23D", "5"], ["G01S", "5"], ["G05D", "5"], ["H04R", "5"], ["A23A", "4"], ["A61F", "4"], ["A61G", "4"], ["A61K", "4"], ["A61M", "4"], ["A63B", "4"], ["A63H", "4"], ["B05B", "4"], ["B23D", "4"], ["B60J", "4"], ["B62A", "4"], ["B66F", "4"], ["C09J", "4"], ["D06F", "4"], ["D06M", "4"], ["E04B", "4"], ["E05D", "4"], ["F02A", "4"], ["F16C", "4"], ["F23Q", "4"], ["F24F", "4"], ["F24H", "4"], ["F27A", "4"], ["H04M", "4"], ["A01C", "3"], ["A41D", "3"], ["A41F", "3"], ["A47C", "3"]], "ipc4": [["A47L9", "8"], ["G01B5", "7"], ["B29C47", "5"], ["C02F1", "5"], ["C08K5", "5"], ["E06B7", "5"], ["H01F21", "5"], ["A01K97", "4"], ["A47G25", "4"], ["A62C13", "4"], ["B01J21", "4"], ["B01J8", "4"], ["B29C35", "4"], ["B60G21", "4"], ["B60G3", "4"], ["D04B15", "4"], ["A01K89", "3"], ["A41F1", "3"], ["A45C11", "3"], ["A45D29", "3"], ["A47J37", "3"], ["B01D3", "3"], ["B23Q5", "3"], ["B60C27", "3"], ["B60S1", "3"], ["B62D49", "3"], ["B65D5", "3"], ["B65H35", "3"], ["C04B28", "3"], ["C07C51", "3"], ["F01L1", "3"], ["F16K31", "3"], ["G07F11", "3"], ["H03K4", "3"], ["A01K93", "2"], ["A24F13", "2"], ["A41B13", "2"], ["A44C5", "2"], ["A45C1", "2"], ["A45C3", "2"], ["A47B13", "2"], ["A47B5", "2"], ["A47C1", "2"], ["A47D1", "2"], ["A47J47", "2"], ["A47K3", "2"], ["A47K5", "2"], ["A47L1", "2"], ["A61B17", "2"], ["A61F2", "2"], ["A61F5", "2"], ["A61M5", "2"], ["B01B1", "2"], ["B01D53", "2"], ["B01J23", "2"], ["B01J37", "2"], ["B05B1", "2"], ["B05B15", "2"], ["B06B1", "2"], ["B23B47", "2"], ["B23K11", "2"], ["B23Q35", "2"], ["B24B3", "2"], ["B24B7", "2"], ["B25B21", "2"], ["B25C5", "2"], ["B29C51", "2"], ["B29C65", "2"], ["B30B15", "2"], ["B41D5", "2"], ["B42D15", "2"], ["B43K24", "2"], ["B60C25", "2"], ["B60D1", "2"], ["B60J3", "2"], ["B60J7", "2"], ["B60P1", "2"], ["B60T11", "2"], ["B61D19", "2"], ["B61L1", "2"], ["B62D11", "2"], ["B65B19", "2"], ["B65G53", "2"], ["B66F7", "2"], ["C07C17", "2"], ["C07C43", "2"], ["C08L9", "2"], ["C09J189", "2"], ["C10G9", "2"], ["C23C18", "2"], ["C23F11", "2"], ["C23G3", "2"], ["D06F37", "2"], ["D06M13", "2"], ["D06M15", "2"], ["E03D5", "2"], ["E04H4", "2"], ["E05F1", "2"], ["E06B3", "2"], ["E21B19", "2"]], "ipc5": [["A47L9/10", "4"], ["B29C35/06", "4"], ["B29C47/00", "4"], ["B60G21/05", "4"], ["H01F21/06", "4"], ["A41F1/00", "3"], ["A45C11/32", "3"], ["A45D29/00", "3"], ["A62C13/00", "3"], ["B62D49/06", "3"], ["B65H35/00", "3"], ["A01K89/06", "2"], ["A01K93/00", "2"], ["A01K97/06", "2"], ["A44C5/20", "2"], ["A47D1/10", "2"], ["A47K5/10", "2"], ["A47L9/28", "2"], ["B01B1/04", "2"], ["B01J21/00", "2"], ["B01J21/12", "2"], ["B01J37/02", "2"], ["B01J8/32", "2"], ["B05B15/02", "2"], ["B23B47/34", "2"], ["B25B21/02", "2"], ["B29C51/18", "2"], ["B29C65/48", "2"], ["B41D5/00", "2"], ["B42D15/08", "2"], ["B43K24/08", "2"], ["B60C25/02", "2"], ["B60G3/26", "2"], ["B60J3/00", "2"], ["B60J7/12", "2"], ["B60T11/224", "2"], ["B61D19/00", "2"], ["B61L1/20", "2"], ["C02F1/72", "2"], ["C02F1/76", "2"], ["C07C43/14", "2"], ["C09J189/00", "2"], ["C10G9/38", "2"], ["C23F11/14", "2"], ["D04B15/54", "2"], ["E06B3/44", "2"], ["E06B7/084", "2"], ["F01L1/25", "2"], ["F16B21/16", "2"], ["F16B37/02", "2"], ["F16D7/04", "2"], ["F16K31/20", "2"], ["F24F3/14", "2"], ["F25B33/00", "2"], ["F25B41/00", "2"], ["G01G19/64", "2"], ["G01G23/365", "2"], ["G01R21/00", "2"], ["G04B19/253", "2"], ["G06G3/00", "2"], ["G07F9/06", "2"], ["G10C3/16", "2"], ["H01Q1/10", "2"], ["A01B23/06", "1"], ["A01B35/02", "1"], ["A01B39/18", "1"], ["A01B49/04", "1"], ["A01B51/02", "1"], ["A01B63/10", "1"], ["A01B63/32", "1"], ["A01C23/04", "1"], ["A01C3/06", "1"], ["A01C7/18", "1"], ["A01D25/04", "1"], ["A01D41/00", "1"], ["A01D45/00", "1"], ["A01D46/247", "1"], ["A01D87/12", "1"], ["A01F12/44", "1"], ["A01G3/06", "1"], ["A01G9/00", "1"], ["A01J21/00", "1"], ["A01K13/00", "1"], ["A01K3/00", "1"], ["A01K59/02", "1"], ["A01K7/04", "1"], ["A01K85/16", "1"], ["A01K89/015", "1"], ["A01K97/10", "1"], ["A01K97/12", "1"], ["A01M17/00", "1"], ["A01M23/24", "1"], ["A01N25/04", "1"], ["A01N25/24", "1"], ["A01N55/08", "1"], ["A21C11/16", "1"], ["A21C13/00", "1"], ["A22C21/02", "1"], ["A22C25/16", "1"], ["A23B7/10", "1"]], "loc": [[null, "0"]]}