{"category": "HR", "countryCode": [["\u514b\u7f57\u5730\u4e9a", "hr", "33791"]], "legalStatus": [["\u672a\u77e5", "33791"]], "applicationYear": [["2021", "689"], ["2020", "1984"], ["2019", "2302"], ["2018", "2215"], ["2017", "2060"], ["2016", "1836"], ["2015", "1484"], ["2014", "1312"], ["2013", "1244"], ["2012", "1101"], ["2011", "1003"], ["2010", "758"], ["2009", "695"], ["2008", "711"], ["2007", "546"], ["2006", "436"], ["2005", "1136"], ["2004", "1442"], ["2003", "1171"], ["2002", "1163"], ["2001", "1042"], ["2000", "953"], ["1999", "385"], ["1998", "715"], ["1997", "811"], ["1996", "673"], ["1995", "576"], ["1994", "1001"], ["1993", "1189"], ["1992", "1158"]], "documentYear": [["2021", "1287"], ["2020", "2197"], ["2019", "2296"], ["2018", "2130"], ["2017", "2076"], ["2016", "1846"], ["2015", "1562"], ["2014", "1301"], ["2013", "1360"], ["2012", "1247"], ["2011", "1221"], ["2010", "861"], ["2009", "954"], ["2008", "834"], ["2007", "754"], ["2006", "937"], ["2005", "1682"], ["2004", "1105"], ["2003", "768"], ["2002", "871"], ["2001", "981"], ["2000", "773"], ["1999", "682"], ["1998", "1010"], ["1997", "991"], ["1996", "1044"], ["1995", "607"], ["1994", "414"]], "applicant": [["HOFFMANN LA ROCHE", "520"], ["JANSSEN PHARMACEUTICA NV", "317"], ["NOVARTIS AG", "292"], ["LILLY CO ELI", "280"], ["PFIZER", "242"], ["PFIZER PROD INC", "216"], ["SERVIER LAB", "184"], ["SQUIBB BRISTOL MYERS CO", "182"], ["GLAXO GROUP LTD", "170"], ["BOEHRINGER INGELHEIM INT", "166"], ["BASF AG", "162"], ["BOEHRINGER INGELHEIM PHARMA", "160"], ["MERCK & CO INC", "158"], ["SANOFI SA", "158"], ["ASTRAZENECA AB", "157"], ["SAMSUNG ELECTRONICS CO LTD", "127"], ["HOECHST AG", "126"], ["LUNDBECK & CO AS H", "116"], ["BAYER AG", "107"], ["AVENTIS PHARMA GMBH", "106"], ["REGENERON PHARMA", "102"], ["BAYER IP GMBH", "101"], ["SANOFI AVENTIS DEUTSCHLAND", "98"], ["GENENTECH INC", "95"], ["SANOFI AVENTIS", "90"], ["MERCK SHARP & DOHME", "88"], ["TEVA PHARMA", "88"], ["AVENTIS PHARMA SA", "87"], ["PLIVA PHARM & CHEM WORKS", "85"], ["WARNER LAMBERT CO", "84"], ["OMYA INT AG", "78"], ["SCHERING AG", "78"], ["BAYER PHARMA AG", "74"], ["MERCK PATENT GMBH", "74"], ["AMGEN INC", "73"], ["CIBA GEIGY AG", "72"], ["VERTEX PHARMA", "68"], ["DEUTSCHE TELEKOM AG", "67"], ["SAINT GOBAIN ISOVER", "67"], ["SYNGENTA PARTICIPATIONS AG", "67"], ["GLAXOSMITHKLINE BIOLOGICALS SA", "65"], ["GILEAD SCIENCES INC", "64"], ["BASF SE", "63"], ["BAYER CROPSCIENCE AG", "62"], ["ASTRA AB", "61"], ["SIEMENS AG", "60"], ["EURO CELTIQUE SA", "57"], ["NESTEC SA", "57"], ["OTSUKA PHARMA CO LTD", "55"], ["FERRING BV", "53"], ["GRUENENTHAL GMBH", "52"], ["HITI IVAN", "51"], ["SANOFI SYNTHELABO", "50"], ["DEGUSSA", "49"], ["ALTANA PHARMA AG", "47"], ["GR\u00dcNENTHAL GMBH", "46"], ["IMMATICS BIOTECHNOLOGIES GMBH", "44"], ["TAKEDA PHARMACEUTICAL", "44"], ["WOBBEN PROPERTIES GMBH", "44"], ["CENTRE NAT RECH SCIENT", "43"], ["AKZO NOBEL NV", "42"], ["BELUPO LIJEKOVI I KOZMETIKA D", "42"], ["LOHMANN THERAPIE SYST LTS", "42"], ["ORION CORP", "42"], ["ARES TRADING SA", "41"], ["ASTELLAS PHARMA INC", "41"], ["TIBOTEC PHARM LTD", "41"], ["ABBVIE INC", "40"], ["GLAXOSMITHKLINE LLC", "39"], ["ISHIHARA SANGYO KAISHA", "39"], ["DART IND INC", "38"], ["GLAXOSMITHKLINE BIOLOG SA", "38"], ["SIGMA TAU IND FARMACEUTI", "38"], ["ACTELION PHARMACEUTICALS LTD", "37"], ["EGYT GYOGYSZERVEGYESZETI GYAR", "37"], ["UCB BIOPHARMA SPRL", "37"], ["CHIESI FARMA SPA", "36"], ["GENZYME CORP", "36"], ["H LUNDBECK AS", "36"], ["BAXALTA GMBH", "35"], ["BAXALTA INC", "34"], ["CHIESI FARM SPA", "34"], ["ARRAY BIOPHARMA INC", "33"], ["RHONE POULENC AGROCHIMIE", "33"], ["SANDOZ AG", "33"], ["BIOGEN MA INC", "32"], ["DAIICHI SANKYO CO LTD", "32"], ["UNIV CALIFORNIA", "32"], ["APPLIED RESEARCH SYSTEMS", "31"], ["BAYER SCHERING PHARMA AG", "31"], ["ASTEX THERAPEUTICS LTD", "30"], ["BAYER HEALTHCARE AG", "30"], ["NOVOMATIC AG", "30"], ["RICHTER GEDEON NYRT", "30"], ["INCYTE HOLDINGS CORP", "29"], ["EGO ELEKTRO BLANC & FISCHER", "28"], ["KRKA", "28"], ["TAKEDA PHARMACEUTICALS CO", "28"], ["VAELINGE INNOVATION AB", "28"], ["CHUGAI PHARMACEUTICAL CO LTD", "27"]], "applicantCountryCode": [["\u514b\u7f57\u5730\u4e9a", "6261"], ["\u7f8e\u56fd", "5243"], ["\u5fb7\u56fd", "4957"], ["\u745e\u58eb", "2275"], ["\u610f\u5927\u5229", "1841"], ["\u6cd5\u56fd", "1782"], ["\u82f1\u56fd", "1164"], ["\u5965\u5730\u5229", "975"], ["\u6bd4\u5229\u65f6", "800"], ["\u8377\u5170", "745"], ["\u65e5\u672c", "665"], ["\u745e\u5178", "596"], ["\u4e39\u9ea6", "495"], ["\u897f\u73ed\u7259", "434"], ["\u5308\u7259\u5229", "307"], ["\u82ac\u5170", "298"], ["\u97e9\u56fd", "296"], ["\u65af\u6d1b\u6587\u5c3c\u4e9a", "279"], ["\u4ee5\u8272\u5217", "240"], ["\u7231\u5c14\u5170", "222"], ["\u52a0\u62ff\u5927", "188"], ["\u632a\u5a01", "181"], ["\u4e2d\u56fd", "171"], ["\u5362\u68ee\u5821", "171"], ["\u5370\u5ea6", "159"], ["\u6377\u514b", "146"], ["\u6ce2\u5170", "117"], ["\u6fb3\u5927\u5229\u4e9a", "109"], ["\u5e0c\u814a", "72"], ["\u8461\u8404\u7259", "53"], ["\u585e\u6d66\u8def\u65af", "49"], ["\u571f\u8033\u5176", "48"], ["\u6ce2\u65af\u5c3c\u4e9a\u548c\u9ed1\u585e\u54e5\u7ef4\u90a3", "47"], ["\u65b0\u52a0\u5761", "46"], ["\u4e2d\u56fd\u53f0\u6e7e", "46"], ["\u4fc4\u7f57\u65af", "45"], ["\u672a\u77e5", "39"], ["\u767e\u6155\u5927", "36"], ["\u5217\u652f\u6566\u58eb\u767b", "35"], ["\u65af\u6d1b\u4f10\u514b", "27"], ["\u58a8\u897f\u54e5", "26"], ["\u5df4\u54c8\u9a6c", "22"], ["\u65b0\u897f\u5170", "22"], ["\u82f1\u5c5e\u7ef4\u5c14\u4eac\u7fa4\u5c9b", "22"], ["\u5e93\u62c9\u7d22", "21"], ["\u5357\u65af\u62c9\u592b", "19"], ["\u53e4\u5df4", "15"], ["\u62c9\u8131\u7ef4\u4e9a", "15"], ["\u4fdd\u52a0\u5229\u4e9a", "14"], ["\u5357\u975e", "14"], ["\u585e\u5c14\u7ef4\u4e9a", "13"], ["\u5df4\u897f", "11"], ["\u5f00\u66fc\u7fa4\u5c9b", "11"], ["\u6469\u7eb3\u54e5", "11"], ["\u667a\u5229", "8"], ["\u9a6c\u8033\u4ed6", "8"], ["\u9a6c\u6765\u897f\u4e9a", "8"], ["\u9ece\u5df4\u5ae9", "6"], ["\u5df4\u62ff\u9a6c", "6"], ["\u7f57\u9a6c\u5c3c\u4e9a", "6"], ["\u963f\u8054\u914b", "5"], ["\u7231\u6c99\u5c3c\u4e9a", "5"], ["\u4e2d\u56fd\u9999\u6e2f", "5"], ["\u51b0\u5c9b", "5"], ["\u5df4\u5df4\u591a\u65af", "4"], ["\u6bdb\u91cc\u6c42\u65af", "4"], ["\u585e\u820c\u5c14", "4"], ["\u963f\u6839\u5ef7", "3"], ["\u5723\u57fa\u8328\u548c\u5c3c\u7ef4\u65af", "3"], ["\u6ce2\u591a\u9ece\u5404", "3"], ["\u6c99\u7279\u963f\u62c9\u4f2f", "3"], ["\u8d8a\u5357", "3"], ["\u5b89\u9053\u5c14", "2"], ["\u963f\u9c81\u5df4", "2"], ["\u671d\u9c9c", "2"], ["\u65af\u91cc\u5170\u5361", "2"], ["\u9a6c\u7ecd\u5c14\u7fa4\u5c9b", "2"], ["\u9a6c\u5176\u987f", "2"], ["\u6cf0\u56fd", "2"], ["\u7a81\u5c3c\u65af", "2"], ["\u4e4c\u514b\u5170", "2"], ["\u4e4c\u62c9\u572d", "2"], ["\u5b89\u63d0\u74dc\u548c\u5df4\u5e03\u8fbe", "1"], ["\u963f\u5c14\u5df4\u5c3c\u4e9a", "1"], ["\u963f\u585e\u62dc\u7586", "1"], ["\u4f2f\u5229\u5179", "1"], ["\u54e5\u4f26\u6bd4\u4e9a", "1"], ["\u54e5\u65af\u8fbe\u9ece\u52a0", "1"], ["\u57c3\u53ca", "1"], ["\u6839\u897f", "1"], ["\u54c8\u8428\u514b\u65af\u5766", "1"], ["\u7acb\u9676\u5b9b", "1"], ["\u6469\u5c14\u591a\u74e6", "1"], ["\u65b0\u5580\u91cc\u591a\u5c3c\u4e9a", "1"], ["\u963f\u66fc", "1"], ["\u83f2\u5f8b\u5bbe", "1"], ["\u4e4d\u5f97", "1"]], "inventor": [["GANE PATRICK A C", "63"], ["MURPHY ANDREW J", "57"], ["KLEEMANN HEINZ-WERNER", "52"], ["HITI IVAN", "51"], ["HAN WOO-JIN", "50"], ["BRENDEL JOACHIM", "48"], ["BURI MATTHIAS", "47"], ["SIMIG GYULA", "46"], ["MACDONALD LYNN", "45"], ["KIM IL-KOO", "40"], ["MIN JUNG-HYE", "40"], ["STEVENS SEAN", "36"], ["ALBUS UDO", "35"], ["CHEON MIN-SU", "35"], ["SAHIN UGUR", "35"], ["WEICHERT ANDREAS", "35"], ["RABOISSON PIERRE JEAN-MARIE BERNARD", "34"], ["WEINSCHENK TONI", "34"], ["SCHOLZ WOLFGANG", "33"], ["SCHWARK JAN-ROBERT", "33"], ["CEPANEC IVICA", "32"], ["PETERSEN HANS", "32"], ["UNGER LILIANE", "32"], ["ROGALE DUBRAVKO", "31"], ["BRKIC BLAGO", "30"], ["NEMET BELA", "30"], ["HEERES JAN", "29"], ["JUNG HAE-KYUNG", "29"], ["ARONHIME JUDITH", "28"], ["BIERINGER HERMANN", "27"], ["LANG HANS JOCHEN", "27"], ["LEE TAMMY", "27"], ["NIKOLIC GOJKO", "27"], ["PERVAN DARKO", "27"], ["SINGH HARPREET", "27"], ["YANG MOONOCK", "27"], ["GLOMBIK HEINER", "26"], ["UMANA PABLO", "26"], ["GERLACH UWE", "25"], ["HACKER ERWIN", "25"], ["OH SOO MI", "25"], ["WALTER STEFFEN", "25"], ["BRKIC GORAN", "24"], ["JAESCHKE GEORG", "24"], ["JASTI VENKATESWARLU", "24"], ["KLEIN CHRISTIAN", "24"], ["MERCEP MLADEN", "24"], ["MESIC MILAN", "24"], ["WIRTH KLAUS", "24"], ["GRETHER UWE", "22"], ["IVICA CEPANEC", "22"], ["JANSSENS FRANS EDUARD", "22"], ["JELASKA DAMIR", "22"], ["REMENAR DAMIR", "22"], ["LANG HANS-JOCHEN", "21"], ["MEERPOEL LIEVEN", "20"], ["SCHAEFER HANS-LUDWIG", "20"], ["DANIJEL \u0110UREK", "19"], ["ROEVER STEPHAN", "19"], ["T\u00dcRECI \u00d6ZLEM", "19"], ["YAO WENQING", "19"], ["HIMMELSBACH FRANK", "18"], ["RENTSCH SAMUEL", "18"], ["SCHIENE KLAUS", "18"], ["STIERL REINHARD", "18"], ["WICHMANN JUERGEN", "18"], ["WILD HANS-PETER", "18"], ["WYLER RENE", "18"], ["DEFOSSA ELISABETH", "17"], ["GURER CAGAN", "17"], ["HEUER HUBERT", "17"], ["HOFFMANN TORSTEN", "17"], ["KO WOO SUK", "17"], ["MOON SANG CHUL", "17"], ["ALSHINA ELENA", "16"], ["DOODS HENRI", "16"], ["GOEGELEIN HEINZ", "16"], ["JAEHNE GERHARD", "16"], ["KEHLER JAN", "16"], ["KU EC JOSIP", "16"], ["LINZ KLAUS", "16"], ["MARX DEGENHARD", "16"], ["PEUEIC DIJANA", "16"], ["PINARD EMMANUEL", "16"], ["RODGERS JAMES D", "16"], ["SCHNIDER PATRICK", "16"], ["BREYER BRANKO", "15"], ["BUETTELMANN BERND", "15"], ["FRICK WENDELIN", "15"], ["HERLING ANDREAS", "15"], ["JONCKERS TIM HUGO MARIA", "15"], ["MAHOVI LEON", "15"], ["MEANWELL NICHOLAS A", "15"], ["SCHOELKOPF JOACHIM", "15"], ["STADLER HEINZ", "15"], ["XU LIANHONG", "15"], ["BARKOCZY JOZSEF", "14"], ["DOLITZKY BEN-ZION", "14"], ["KADEREIT DIETER", "14"], ["LECOMTE JEANNE-MARIE", "14"]], "ipc": [["A61P35/00", "2466"], ["A61P43/00", "1888"], ["A61P29/00", "1408"], ["A61P25/00", "1308"], ["A61P25/28", "1095"], ["A61P9/00", "1008"], ["A61P9/10", "988"], ["C07D401/12", "987"], ["A61K9/00", "949"], ["C07D471/04", "932"], ["A61K45/06", "807"], ["C07D401/14", "800"], ["A61P3/10", "794"], ["C07D487/04", "793"], ["A61P11/00", "787"], ["A61K39/395", "744"], ["A61K9/20", "695"], ["C07D401/04", "665"], ["A61K38/00", "635"], ["A61K31/44", "626"], ["A61P11/06", "623"], ["A61K31/4439", "621"], ["C07D405/12", "614"], ["A61P31/04", "609"], ["A61K31/5377", "608"], ["A61K31/506", "595"], ["A61P19/02", "584"], ["C07K16/28", "558"], ["C07D413/14", "556"], ["A61K20060101", "551"], ["A61P37/00", "546"], ["A61K31/496", "540"], ["C07D403/12", "540"], ["A61K31/519", "528"], ["C07D417/12", "526"], ["A61K39/00", "524"], ["A61K31/00", "519"], ["A61P17/00", "517"], ["A61P25/24", "514"], ["A61P1/04", "512"], ["A61K31/505", "501"], ["C07D417/14", "498"], ["A61K31/40", "496"], ["C07D413/12", "494"], ["A61P1/00", "486"], ["A61K45/00", "474"], ["A61K31/55", "469"], ["A61K31/445", "461"], ["A61P31/12", "459"], ["A61K31/495", "449"], ["C07D405/14", "442"], ["C07D20060101", "440"], ["A61P25/18", "436"], ["C07D401/06", "428"], ["A61P17/06", "419"], ["A61K31/437", "412"], ["A61P25/16", "412"], ["A61P9/12", "409"], ["A61P25/04", "408"], ["A61P27/02", "406"], ["A61P31/18", "405"], ["A61K9/16", "394"], ["A61P15/00", "394"], ["C07D409/12", "382"], ["A61P37/08", "380"], ["A61P25/22", "377"], ["A61K31/47", "369"], ["A61K47/10", "364"], ["A61K9/08", "358"], ["A61P3/04", "358"], ["A61K47/26", "354"], ["A61P13/12", "354"], ["C07D403/04", "352"], ["A61K31/4709", "337"], ["A61K31/415", "334"], ["A61P3/06", "334"], ["A61K31/454", "333"], ["A61P37/06", "329"], ["C07D413/04", "320"], ["A61K9/48", "312"], ["C07D409/14", "311"], ["A61K9/14", "305"], ["A61K31/404", "298"], ["A61K31/70", "294"], ["A61P7/02", "292"], ["A61K47/12", "287"], ["A61P31/00", "284"], ["A61K31/4184", "279"], ["A61P37/02", "277"], ["A61K47/38", "275"], ["A61P25/08", "274"], ["A61K31/435", "272"], ["A61P3/00", "271"], ["C12N15/09", "269"], ["C07D403/14", "267"], ["A61P1/16", "264"], ["A61P19/10", "259"], ["A61K9/28", "254"], ["A61K31/4427", "252"], ["A61P17/02", "249"]], "ipc1": [["A", "17995"], ["C", "14208"], ["B", "5995"], ["F", "3179"], ["E", "2657"], ["G", "2477"], ["H", "2044"], ["D", "506"]], "ipc2": [["A61", "14243"], ["C07", "10689"], ["C12", "1988"], ["A01", "1746"], ["B65", "1328"], ["G01", "1155"], ["E04", "1130"], ["F16", "991"], ["B01", "884"], ["A47", "875"], ["C08", "779"], ["A23", "776"], ["H04", "774"], ["B63", "665"], ["H01", "648"], ["B60", "573"], ["H02", "568"], ["G06", "518"], ["F24", "500"], ["B29", "466"], ["C09", "456"], ["E01", "407"], ["C02", "353"], ["F03", "345"], ["B32", "342"], ["E02", "338"], ["E05", "337"], ["A63", "302"], ["C04", "299"], ["C10", "295"], ["E06", "284"], ["B23", "274"], ["F02", "260"], ["C01", "251"], ["E03", "233"], ["B62", "229"], ["C03", "215"], ["F41", "212"], ["B05", "210"], ["G07", "209"], ["G09", "207"], ["F01", "201"], ["B21", "195"], ["B61", "192"], ["H05", "189"], ["G08", "184"], ["F04", "180"], ["F23", "177"], ["C22", "170"], ["B67", "156"], ["D21", "156"], ["E21", "154"], ["A41", "153"], ["A62", "153"], ["D06", "153"], ["B66", "150"], ["B25", "138"], ["G05", "135"], ["C11", "131"], ["A21", "129"], ["F25", "126"], ["A24", "125"], ["B27", "125"], ["D04", "125"], ["C23", "124"], ["F28", "120"], ["A43", "119"], ["C21", "118"], ["F21", "118"], ["A45", "115"], ["F17", "111"], ["B41", "110"], ["C05", "108"], ["B26", "107"], ["B22", "105"], ["B09", "104"], ["B28", "98"], ["G02", "95"], ["F27", "92"], ["B44", "84"], ["B64", "83"], ["B42", "82"], ["F42", "79"], ["D01", "78"], ["B08", "75"], ["B31", "74"], ["B02", "72"], ["C25", "70"], ["F26", "65"], ["G10", "65"], ["H03", "63"], ["B03", "60"], ["G03", "57"], ["A22", "55"], ["B24", "53"], ["B07", "51"], ["A42", "46"], ["F22", "45"], ["G21", "42"], ["A46", "39"]], "ipc3": [["A61K", "12753"], ["A61P", "9356"], ["C07D", "7110"], ["C07K", "2387"], ["C07C", "1708"], ["C12N", "1439"], ["A01N", "1000"], ["B65D", "952"], ["G01N", "753"], ["C07H", "552"], ["C12P", "529"], ["A61M", "522"], ["A23L", "506"], ["B01D", "453"], ["C07F", "451"], ["B63B", "449"], ["E04B", "423"], ["B29C", "385"], ["B01J", "360"], ["C07B", "359"], ["C02F", "352"], ["A01K", "349"], ["C12Q", "346"], ["B32B", "342"], ["F16L", "340"], ["A61F", "334"], ["A61L", "330"], ["A61B", "308"], ["C08L", "300"], ["C04B", "299"], ["E04F", "288"], ["A01P", "285"], ["E04C", "274"], ["H04N", "272"], ["G06F", "266"], ["E06B", "261"], ["A47J", "257"], ["H04L", "246"], ["A61Q", "232"], ["E04H", "223"], ["F16B", "220"], ["C09D", "210"], ["B63H", "209"], ["C08J", "199"], ["E05B", "193"], ["C07J", "187"], ["F03D", "183"], ["C08K", "180"], ["E01B", "180"], ["B65G", "175"], ["C08G", "174"], ["H04W", "173"], ["B65B", "172"], ["H02K", "171"], ["A61J", "169"], ["H01H", "168"], ["G06Q", "166"], ["C08F", "164"], ["A47C", "163"], ["C12R", "156"], ["C01B", "155"], ["G09F", "146"], ["A01G", "144"], ["E02D", "144"], ["F16K", "139"], ["E02B", "137"], ["F24F", "137"], ["C03B", "133"], ["B05B", "130"], ["A47G", "129"], ["F02B", "126"], ["A63B", "125"], ["H02G", "125"], ["A61H", "123"], ["B01F", "123"], ["A47B", "121"], ["C08B", "121"], ["G07F", "121"], ["B67D", "119"], ["D21H", "118"], ["C03C", "115"], ["F03B", "115"], ["F24D", "115"], ["A61N", "114"], ["B60R", "113"], ["F24S", "113"], ["H05B", "112"], ["C10L", "111"], ["E04D", "110"], ["E01F", "108"], ["A47K", "107"], ["H01R", "106"], ["C09C", "105"], ["B23K", "104"], ["A62C", "103"], ["C10G", "103"], ["F04D", "102"], ["H01L", "102"], ["A43B", "101"], ["H04B", "100"]], "ipc4": [["A61K31", "9599"], ["A61P25", "2571"], ["A61P35", "2539"], ["A61K9", "2418"], ["C07D401", "1962"], ["A61P43", "1888"], ["A61P9", "1808"], ["A61P31", "1592"], ["A61K47", "1539"], ["A61K38", "1538"], ["A61P3", "1444"], ["A61P29", "1427"], ["A61K39", "1345"], ["A61P1", "1222"], ["C07D471", "1217"], ["C07D413", "1216"], ["A61P37", "1206"], ["C07K16", "1198"], ["A61P11", "1175"], ["A61K45", "1169"], ["C07D405", "1143"], ["C07D417", "1135"], ["C07D403", "1114"], ["C07D487", "1017"], ["C07K14", "952"], ["A61P17", "947"], ["C12N15", "923"], ["A61P19", "897"], ["C07D409", "802"], ["C07D213", "771"], ["A61P13", "751"], ["A61P15", "639"], ["G01N33", "620"], ["A01N43", "615"], ["A61P7", "607"], ["A61P27", "600"], ["C07D239", "582"], ["C07D209", "553"], ["A61K20060101", "551"], ["C07D211", "474"], ["C07D20060101", "440"], ["C07D207", "436"], ["C07D491", "430"], ["C07D295", "408"], ["A61P5", "403"], ["A61K35", "398"], ["C12N5", "393"], ["C07D215", "382"], ["C07D307", "375"], ["C07D231", "346"], ["C07D498", "346"], ["C12Q1", "346"], ["C07D233", "337"], ["C07D277", "327"], ["C07D495", "308"], ["C12N9", "305"], ["C07D333", "300"], ["C12P21", "296"], ["A61P21", "292"], ["C12N1", "286"], ["E04B1", "280"], ["A61K36", "268"], ["C07K5", "260"], ["C07D241", "259"], ["A01N25", "255"], ["A61P33", "255"], ["C07K7", "250"], ["A61K8", "249"], ["C07C233", "242"], ["C07D519", "242"], ["C07F9", "227"], ["C02F1", "226"], ["C07D235", "224"], ["C07K1", "224"], ["A01N47", "223"], ["C07C311", "222"], ["C07D407", "213"], ["A61K33", "211"], ["C07D513", "211"], ["C07B61", "207"], ["C07C323", "203"], ["A61K48", "202"], ["C07D263", "197"], ["C07D249", "195"], ["A01N37", "183"], ["C07C229", "181"], ["H04N19", "179"], ["C07C255", "177"], ["B65D85", "176"], ["C07H17", "175"], ["A61M15", "173"], ["C07H19", "170"], ["C07D217", "166"], ["A61Q19", "163"], ["C07D521", "163"], ["C07C317", "161"], ["A61M5", "159"], ["C07C69", "159"], ["A61P20060101", "157"], ["C12R1", "156"]], "ipc5": [["A61P35/00", "2466"], ["A61P43/00", "1888"], ["A61P29/00", "1408"], ["A61P25/00", "1308"], ["A61P25/28", "1095"], ["A61P9/00", "1008"], ["A61P9/10", "988"], ["C07D401/12", "987"], ["A61K9/00", "949"], ["C07D471/04", "932"], ["A61K45/06", "807"], ["C07D401/14", "800"], ["A61P3/10", "794"], ["C07D487/04", "793"], ["A61P11/00", "787"], ["A61K39/395", "744"], ["A61K9/20", "695"], ["C07D401/04", "665"], ["A61K38/00", "635"], ["A61K31/44", "626"], ["A61P11/06", "623"], ["A61K31/4439", "621"], ["C07D405/12", "614"], ["A61P31/04", "609"], ["A61K31/5377", "608"], ["A61K31/506", "595"], ["A61P19/02", "584"], ["C07K16/28", "558"], ["C07D413/14", "556"], ["A61P37/00", "546"], ["A61K31/496", "540"], ["C07D403/12", "540"], ["A61K31/519", "528"], ["C07D417/12", "526"], ["A61K39/00", "524"], ["A61K31/00", "519"], ["A61P17/00", "517"], ["A61P25/24", "514"], ["A61P1/04", "512"], ["A61K31/505", "501"], ["C07D417/14", "498"], ["A61K31/40", "496"], ["C07D413/12", "494"], ["A61P1/00", "486"], ["A61K45/00", "474"], ["A61K31/55", "469"], ["A61K31/445", "461"], ["A61P31/12", "459"], ["A61K31/495", "449"], ["C07D405/14", "442"], ["A61P25/18", "436"], ["C07D401/06", "428"], ["A61P17/06", "419"], ["A61K31/437", "412"], ["A61P25/16", "412"], ["A61P9/12", "409"], ["A61P25/04", "408"], ["A61P27/02", "406"], ["A61P31/18", "405"], ["A61K9/16", "394"], ["A61P15/00", "394"], ["C07D409/12", "382"], ["A61P37/08", "380"], ["A61P25/22", "377"], ["A61K31/47", "369"], ["A61K47/10", "364"], ["A61K9/08", "358"], ["A61P3/04", "358"], ["A61K47/26", "354"], ["A61P13/12", "354"], ["C07D403/04", "352"], ["A61K31/4709", "337"], ["A61K31/415", "334"], ["A61P3/06", "334"], ["A61K31/454", "333"], ["A61P37/06", "329"], ["C07D413/04", "320"], ["A61K9/48", "312"], ["C07D409/14", "311"], ["A61K9/14", "305"], ["A61K31/404", "298"], ["A61K31/70", "294"], ["A61P7/02", "292"], ["A61K47/12", "287"], ["A61P31/00", "284"], ["A61K31/4184", "279"], ["A61P37/02", "277"], ["A61K47/38", "275"], ["A61P25/08", "274"], ["A61K31/435", "272"], ["A61P3/00", "271"], ["C12N15/09", "269"], ["C07D403/14", "267"], ["A61P1/16", "264"], ["A61P19/10", "259"], ["A61K9/28", "254"], ["A61K31/4427", "252"], ["A61P17/02", "249"], ["C07D405/04", "243"], ["A61K31/427", "242"]], "loc": [[null, "0"]]}