{"category": "KG", "countryCode": [["\u5409\u5c14\u5409\u65af\u65af\u5766", "kg", "7"]], "legalStatus": [["\u672a\u77e5", "7"]], "applicationYear": [["2012", "1"], ["2010", "1"], ["2008", "2"], ["2007", "1"], ["2002", "1"], ["2001", "1"]], "documentYear": [["2012", "1"], ["2011", "1"], ["2009", "2"], ["2008", "1"], ["2003", "1"], ["2002", "1"]], "applicant": [["DIKAMBAEVA M K", "1"], ["IMANBAEVA S S", "1"], ["MEDVEDEV M A", "1"], ["POLYAK A", "1"], ["SHIPILOV V N", "1"], ["TAZHIBAEV T D", "1"], ["TURGUNBAEV N A", "1"]], "applicantCountryCode": [["\u5409\u5c14\u5409\u65af\u65af\u5766", "2"]], "inventor": [["DIKAMBAEVA M K", "1"], ["IMANBAEVA S S", "1"], ["MEDVEDEV M A", "1"], ["POLYAK A", "1"], ["SHIPILOV V N", "1"], ["TAZHIBAEV T D", "1"], ["TURGUNBAEV N A", "1"]], "ipc": [[null, "0"]], "ipc1": [[null, "0"]], "ipc2": [[null, "0"]], "ipc3": [[null, "0"]], "ipc4": [[null, "0"]], "ipc5": [[null, "0"]], "loc": [[null, "0"]]}